{
  "checkedBySkill": {
    "baking": 109,
    "smithing": 144,
    "pottery": 53,
    "fletching": 113,
    "tailoring": 127,
    "tinkering": 16,
    "brewing": 80
  },
  "enrichedBySkill": {
    "baking": 106,
    "smithing": 120,
    "pottery": 35,
    "fletching": 23,
    "tailoring": 124,
    "tinkering": 15,
    "brewing": 76
  },
  "unresolved": [
    {
      "skill": "baking",
      "name": "Dragon Steak",
      "reason": "No exact Allakhazam item match found."
    },
    {
      "skill": "baking",
      "name": "Fillets",
      "reason": "No exact Allakhazam item match found."
    },
    {
      "skill": "baking",
      "name": "Snow Bunny Stew",
      "reason": "No exact Allakhazam item match found."
    },
    {
      "skill": "smithing",
      "name": "Shaped Cookie Cutters",
      "reason": "No exact Allakhazam item match found."
    },
    {
      "skill": "smithing",
      "name": "Sewing Kit",
      "reason": "No exact Allakhazam item match found."
    },
    {
      "skill": "smithing",
      "name": "Bracer",
      "reason": "No exact Allakhazam item match found."
    },
    {
      "skill": "smithing",
      "name": "Gorget",
      "reason": "No exact Allakhazam item match found."
    },
    {
      "skill": "smithing",
      "name": "Mask",
      "reason": "No exact Allakhazam item match found."
    },
    {
      "skill": "smithing",
      "name": "Boots",
      "reason": "No exact Allakhazam item match found."
    },
    {
      "skill": "smithing",
      "name": "Gauntlets",
      "reason": "No exact Allakhazam item match found."
    },
    {
      "skill": "smithing",
      "name": "Sleeves",
      "reason": "No exact Allakhazam item match found."
    },
    {
      "skill": "smithing",
      "name": "Leggings",
      "reason": "No exact Allakhazam item match found."
    },
    {
      "skill": "smithing",
      "name": "Cloak",
      "reason": "No exact Allakhazam item match found."
    },
    {
      "skill": "smithing",
      "name": "Mantle",
      "reason": "No exact Allakhazam item match found."
    },
    {
      "skill": "smithing",
      "name": "Helm",
      "reason": "No exact Allakhazam item match found."
    },
    {
      "skill": "smithing",
      "name": "Veil",
      "reason": "No exact Allakhazam item match found."
    },
    {
      "skill": "smithing",
      "name": "Bracelet",
      "reason": "No exact Allakhazam item match found."
    },
    {
      "skill": "smithing",
      "name": "Mail",
      "reason": "No exact Allakhazam item match found."
    },
    {
      "skill": "smithing",
      "name": "Coif",
      "reason": "No exact Allakhazam item match found."
    },
    {
      "skill": "smithing",
      "name": "Collar",
      "reason": "No exact Allakhazam item match found."
    },
    {
      "skill": "smithing",
      "name": "Girdle",
      "reason": "No exact Allakhazam item match found."
    },
    {
      "skill": "smithing",
      "name": "Pauldron",
      "reason": "No exact Allakhazam item match found."
    },
    {
      "skill": "smithing",
      "name": "Visor",
      "reason": "No exact Allakhazam item match found."
    },
    {
      "skill": "smithing",
      "name": "Gloves",
      "reason": "No exact Allakhazam item match found."
    },
    {
      "skill": "smithing",
      "name": "Vambraces",
      "reason": "No exact Allakhazam item match found."
    },
    {
      "skill": "smithing",
      "name": "Greaves",
      "reason": "No exact Allakhazam item match found."
    },
    {
      "skill": "smithing",
      "name": "Breastplate",
      "reason": "No exact Allakhazam item match found."
    },
    {
      "skill": "fletching",
      "name": "Hickory, Hemp",
      "reason": "No exact Allakhazam item match found."
    },
    {
      "skill": "fletching",
      "name": "Hickory, Silk",
      "reason": "No exact Allakhazam item match found."
    },
    {
      "skill": "fletching",
      "name": "Hickory, Linen",
      "reason": "No exact Allakhazam item match found."
    },
    {
      "skill": "fletching",
      "name": "Elm, Hemp",
      "reason": "No exact Allakhazam item match found."
    },
    {
      "skill": "fletching",
      "name": "Elm, Linen",
      "reason": "No exact Allakhazam item match found."
    },
    {
      "skill": "fletching",
      "name": "Carved Elm, Hemp",
      "reason": "No exact Allakhazam item match found."
    },
    {
      "skill": "fletching",
      "name": "Elm, Silk",
      "reason": "No exact Allakhazam item match found."
    },
    {
      "skill": "fletching",
      "name": "Carved Elm, Linen",
      "reason": "No exact Allakhazam item match found."
    },
    {
      "skill": "fletching",
      "name": "Carved Elm, Silk",
      "reason": "No exact Allakhazam item match found."
    },
    {
      "skill": "fletching",
      "name": "Ash, Hemp",
      "reason": "No exact Allakhazam item match found."
    },
    {
      "skill": "fletching",
      "name": "Ash, Silk",
      "reason": "No exact Allakhazam item match found."
    },
    {
      "skill": "fletching",
      "name": "Ash, Linen",
      "reason": "No exact Allakhazam item match found."
    },
    {
      "skill": "fletching",
      "name": "Carved Ash, Linen",
      "reason": "No exact Allakhazam item match found."
    },
    {
      "skill": "fletching",
      "name": "Carved Ash, Hemp",
      "reason": "No exact Allakhazam item match found."
    },
    {
      "skill": "fletching",
      "name": "Carved Ash, Silk",
      "reason": "No exact Allakhazam item match found."
    },
    {
      "skill": "fletching",
      "name": "Shaped Ash, Linen",
      "reason": "No exact Allakhazam item match found."
    },
    {
      "skill": "fletching",
      "name": "Shaped Ash, Hemp",
      "reason": "No exact Allakhazam item match found."
    },
    {
      "skill": "fletching",
      "name": "Shaped Ash, Silk",
      "reason": "No exact Allakhazam item match found."
    },
    {
      "skill": "fletching",
      "name": "Oak, Linen",
      "reason": "No exact Allakhazam item match found."
    },
    {
      "skill": "fletching",
      "name": "Oak, Hemp",
      "reason": "No exact Allakhazam item match found."
    },
    {
      "skill": "fletching",
      "name": "Oak, Silk",
      "reason": "No exact Allakhazam item match found."
    },
    {
      "skill": "fletching",
      "name": "Carved Oak, Hemp",
      "reason": "No exact Allakhazam item match found."
    },
    {
      "skill": "fletching",
      "name": "Carved Oak, Linen",
      "reason": "No exact Allakhazam item match found."
    },
    {
      "skill": "fletching",
      "name": "Shaped Oak, Hemp",
      "reason": "No exact Allakhazam item match found."
    },
    {
      "skill": "fletching",
      "name": "Carved Oak, Silk",
      "reason": "No exact Allakhazam item match found."
    },
    {
      "skill": "fletching",
      "name": "Shaped Oak, Linen",
      "reason": "No exact Allakhazam item match found."
    },
    {
      "skill": "fletching",
      "name": "1-Cam Oak, Silk",
      "reason": "No exact Allakhazam item match found."
    },
    {
      "skill": "fletching",
      "name": "Shaped Oak, Silk",
      "reason": "No exact Allakhazam item match found."
    },
    {
      "skill": "fletching",
      "name": "1-Cam Oak, Linen",
      "reason": "No exact Allakhazam item match found."
    },
    {
      "skill": "fletching",
      "name": "1-Cam Carved Oak, Hemp",
      "reason": "No exact Allakhazam item match found."
    },
    {
      "skill": "fletching",
      "name": "1-Cam Oak, Hemp",
      "reason": "No exact Allakhazam item match found."
    },
    {
      "skill": "fletching",
      "name": "1-Cam Shaped Oak, Hemp",
      "reason": "No exact Allakhazam item match found."
    },
    {
      "skill": "fletching",
      "name": "1-Cam Carved Oak, Linen",
      "reason": "No exact Allakhazam item match found."
    },
    {
      "skill": "fletching",
      "name": "1-Cam Carved Oak, Silk",
      "reason": "No exact Allakhazam item match found."
    },
    {
      "skill": "fletching",
      "name": "1-Cam Shaped Oak, Linen",
      "reason": "No exact Allakhazam item match found."
    },
    {
      "skill": "fletching",
      "name": "1-Cam Shaped Oak, Silk",
      "reason": "No exact Allakhazam item match found."
    },
    {
      "skill": "fletching",
      "name": "Darkwood, Hemp",
      "reason": "No exact Allakhazam item match found."
    },
    {
      "skill": "fletching",
      "name": "Darkwood, Silk",
      "reason": "No exact Allakhazam item match found."
    },
    {
      "skill": "fletching",
      "name": "Darkwood, Linen",
      "reason": "No exact Allakhazam item match found."
    },
    {
      "skill": "fletching",
      "name": "Carved Darkwood, Linen",
      "reason": "No exact Allakhazam item match found."
    },
    {
      "skill": "fletching",
      "name": "Carved Darkwood, Hemp",
      "reason": "No exact Allakhazam item match found."
    },
    {
      "skill": "fletching",
      "name": "Carved Darkwood, Silk",
      "reason": "No exact Allakhazam item match found."
    },
    {
      "skill": "fletching",
      "name": "Shaped Darkwood, Linen",
      "reason": "No exact Allakhazam item match found."
    },
    {
      "skill": "fletching",
      "name": "Shaped Darkwood, Hemp",
      "reason": "No exact Allakhazam item match found."
    },
    {
      "skill": "fletching",
      "name": "1-Cam Darkwood, Hemp",
      "reason": "No exact Allakhazam item match found."
    },
    {
      "skill": "fletching",
      "name": "Shaped Darkwood, Silk",
      "reason": "No exact Allakhazam item match found."
    },
    {
      "skill": "fletching",
      "name": "1-Cam Darkwood, Linen",
      "reason": "No exact Allakhazam item match found."
    },
    {
      "skill": "fletching",
      "name": "1-Cam Darkwood, Silk",
      "reason": "No exact Allakhazam item match found."
    },
    {
      "skill": "fletching",
      "name": "1-Cam Carved Darkwood, Hemp",
      "reason": "No exact Allakhazam item match found."
    },
    {
      "skill": "fletching",
      "name": "1-Cam Carved Darkwood, Linen",
      "reason": "No exact Allakhazam item match found."
    },
    {
      "skill": "fletching",
      "name": "1-Cam Carved Darkwood, Silk",
      "reason": "No exact Allakhazam item match found."
    },
    {
      "skill": "fletching",
      "name": "1-Cam Shaped Darkwood, Hemp",
      "reason": "No exact Allakhazam item match found."
    },
    {
      "skill": "fletching",
      "name": "1-Cam Shaped Darkwood, Linen",
      "reason": "No exact Allakhazam item match found."
    },
    {
      "skill": "fletching",
      "name": "Compound Darkwood, Hemp",
      "reason": "No exact Allakhazam item match found."
    },
    {
      "skill": "fletching",
      "name": "1-Cam Shaped Darkwood, Silk",
      "reason": "No exact Allakhazam item match found."
    },
    {
      "skill": "fletching",
      "name": "Compound Darkwood, Linen",
      "reason": "No exact Allakhazam item match found."
    },
    {
      "skill": "fletching",
      "name": "Compound Darkwood, Silk",
      "reason": "No exact Allakhazam item match found."
    },
    {
      "skill": "fletching",
      "name": "Compound Carved Darkwood, Hemp",
      "reason": "No exact Allakhazam item match found."
    },
    {
      "skill": "fletching",
      "name": "Compound Carved Darkwood, Linen",
      "reason": "No exact Allakhazam item match found."
    },
    {
      "skill": "fletching",
      "name": "Compound Carved Darkwood, Silk",
      "reason": "No exact Allakhazam item match found."
    },
    {
      "skill": "fletching",
      "name": "Compound Shaped Darkwood, Hemp",
      "reason": "No exact Allakhazam item match found."
    },
    {
      "skill": "fletching",
      "name": "Compound Shaped Darkwood, Linen",
      "reason": "No exact Allakhazam item match found."
    },
    {
      "skill": "fletching",
      "name": "Compound Shaped Darkwood, Silk",
      "reason": "No exact Allakhazam item match found."
    },
    {
      "skill": "fletching",
      "name": "Shadewood,Linen",
      "reason": "No exact Allakhazam item match found."
    },
    {
      "skill": "fletching",
      "name": "Shadewood,Hemp",
      "reason": "No exact Allakhazam item match found."
    },
    {
      "skill": "fletching",
      "name": "Shadewood, Silk",
      "reason": "No exact Allakhazam item match found."
    },
    {
      "skill": "fletching",
      "name": "Carved Shadewood, Hemp",
      "reason": "No exact Allakhazam item match found."
    },
    {
      "skill": "fletching",
      "name": "Carved Shadewood, Linen",
      "reason": "No exact Allakhazam item match found."
    },
    {
      "skill": "fletching",
      "name": "Carved Shadewood, Silk",
      "reason": "No exact Allakhazam item match found."
    },
    {
      "skill": "fletching",
      "name": "Shaped Shadewood, Hemp",
      "reason": "No exact Allakhazam item match found."
    },
    {
      "skill": "fletching",
      "name": "Shaped Shadewood, Silk",
      "reason": "No exact Allakhazam item match found."
    },
    {
      "skill": "fletching",
      "name": "1-Cam Shadewood, Hemp",
      "reason": "No exact Allakhazam item match found."
    },
    {
      "skill": "fletching",
      "name": "Shaped Shadewood, Linen",
      "reason": "No exact Allakhazam item match found."
    },
    {
      "skill": "fletching",
      "name": "1-Cam Shadewood, Linen",
      "reason": "No exact Allakhazam item match found."
    },
    {
      "skill": "fletching",
      "name": "1-Cam Shadewood, Silk",
      "reason": "No exact Allakhazam item match found."
    },
    {
      "skill": "fletching",
      "name": "1-Cam Carved Shadewood, Hemp",
      "reason": "No exact Allakhazam item match found."
    },
    {
      "skill": "fletching",
      "name": "1-Cam Carved Shadewood, Linen",
      "reason": "No exact Allakhazam item match found."
    },
    {
      "skill": "fletching",
      "name": "1-Cam Carved Shadewood, Silk",
      "reason": "No exact Allakhazam item match found."
    },
    {
      "skill": "fletching",
      "name": "1-Cam Shaped Shadewood, Hemp",
      "reason": "No exact Allakhazam item match found."
    },
    {
      "skill": "fletching",
      "name": "1-Cam Shaped Shadewood, Linen",
      "reason": "No exact Allakhazam item match found."
    },
    {
      "skill": "fletching",
      "name": "1-Cam Shaped Shadewood, Silk",
      "reason": "No exact Allakhazam item match found."
    },
    {
      "skill": "fletching",
      "name": "Compound Shadewood, Hemp",
      "reason": "No exact Allakhazam item match found."
    },
    {
      "skill": "fletching",
      "name": "Compound Shadewood, Linen",
      "reason": "No exact Allakhazam item match found."
    },
    {
      "skill": "fletching",
      "name": "Compound Shadewood, Silk",
      "reason": "No exact Allakhazam item match found."
    },
    {
      "skill": "fletching",
      "name": "Compound Carved Shadewood, Linen",
      "reason": "No exact Allakhazam item match found."
    },
    {
      "skill": "fletching",
      "name": "Compound Carved Shadewood, Hemp",
      "reason": "No exact Allakhazam item match found."
    },
    {
      "skill": "fletching",
      "name": "Compound Carved Shadewood, Silk",
      "reason": "No exact Allakhazam item match found."
    },
    {
      "skill": "fletching",
      "name": "Compound Shaped Shadewood, Hemp",
      "reason": "No exact Allakhazam item match found."
    },
    {
      "skill": "fletching",
      "name": "Compound Shaped Shadewood, Linen",
      "reason": "No exact Allakhazam item match found."
    },
    {
      "skill": "fletching",
      "name": "Compound Shaped Shadewood, Silk",
      "reason": "No exact Allakhazam item match found."
    },
    {
      "skill": "pottery",
      "name": "Sketch",
      "reason": "No exact Allakhazam item match found."
    },
    {
      "skill": "pottery",
      "name": "Imbued Gem",
      "reason": "No exact Allakhazam item match found."
    },
    {
      "skill": "pottery",
      "name": "Fired Idol",
      "reason": "No exact Allakhazam item match found."
    },
    {
      "skill": "tailoring",
      "name": "Reinforced Armor",
      "reason": "No exact Allakhazam item match found."
    },
    {
      "skill": "tailoring",
      "name": "Crystalline Silk Armor Set",
      "reason": "No exact Allakhazam item match found."
    },
    {
      "skill": "tailoring",
      "name": "Ice Silk Armor Set",
      "reason": "No exact Allakhazam item match found."
    },
    {
      "skill": "tinkering",
      "name": "Gnomish Vanishing Device",
      "reason": "No exact Allakhazam item match found."
    },
    {
      "skill": "brewing",
      "name": "Thubr",
      "reason": "No exact Allakhazam item match found."
    },
    {
      "skill": "brewing",
      "name": "Ol",
      "reason": "No exact Allakhazam item match found."
    },
    {
      "skill": "brewing",
      "name": "Lothran",
      "reason": "No exact Allakhazam item match found."
    },
    {
      "skill": "brewing",
      "name": "Minotaur Hero",
      "reason": "No exact Allakhazam item match found."
    }
  ],
  "ambiguous": [
    {
      "skill": "baking",
      "name": "Wedding Cake",
      "candidates": [
        {
          "url": "https://everquest.allakhazam.com/db/item.html?item=15081",
          "text": "Wedding Cake"
        },
        {
          "url": "https://everquest.allakhazam.com/db/item.html?item=49281",
          "text": "Wedding Cake [GM item]"
        },
        {
          "url": "https://everquest.allakhazam.com/db/item.html?item=116075",
          "text": "Wedding Cake"
        }
      ]
    },
    {
      "skill": "baking",
      "name": "Birthday Cake",
      "candidates": [
        {
          "url": "https://everquest.allakhazam.com/db/item.html?item=15022",
          "text": "Birthday Cake [ID 16562]"
        },
        {
          "url": "https://everquest.allakhazam.com/db/item.html?item=89402",
          "text": "Birthday Cake"
        },
        {
          "url": "https://everquest.allakhazam.com/db/item.html?item=49545",
          "text": "Birthday Cake [ID 31871]"
        }
      ]
    },
    {
      "skill": "baking",
      "name": "Loaf of Bread",
      "candidates": [
        {
          "url": "https://everquest.allakhazam.com/db/item.html?item=7881",
          "text": "Loaf of Bread"
        },
        {
          "url": "https://everquest.allakhazam.com/db/item.html?item=115045",
          "text": "Loaf of Bread"
        }
      ]
    },
    {
      "skill": "baking",
      "name": "Mammoth Sandwich",
      "candidates": [
        {
          "url": "https://everquest.allakhazam.com/db/item.html?item=60374",
          "text": "Mammoth Sandwich"
        },
        {
          "url": "https://everquest.allakhazam.com/db/item.html?item=15054",
          "text": "Mammoth Sandwich"
        }
      ]
    },
    {
      "skill": "baking",
      "name": "Muffin",
      "candidates": [
        {
          "url": "https://everquest.allakhazam.com/db/item.html?item=49763",
          "text": "Muffin [crafted]"
        },
        {
          "url": "https://everquest.allakhazam.com/db/item.html?item=3448",
          "text": "Muffin"
        }
      ]
    },
    {
      "skill": "baking",
      "name": "Rabbit Stew",
      "candidates": [
        {
          "url": "https://everquest.allakhazam.com/db/item.html?item=15065",
          "text": "Rabbit Stew"
        },
        {
          "url": "https://everquest.allakhazam.com/db/item.html?item=49560",
          "text": "Rabbit Stew [ID 11350]"
        }
      ]
    },
    {
      "skill": "baking",
      "name": "White Chocolate Cookies",
      "candidates": [
        {
          "url": "https://everquest.allakhazam.com/db/item.html?item=31818",
          "text": "White Chocolate Cookies [Now brownie free!]"
        },
        {
          "url": "https://everquest.allakhazam.com/db/item.html?item=15084",
          "text": "White Chocolate Cookies"
        }
      ]
    },
    {
      "skill": "smithing",
      "name": "Sheet Metal",
      "candidates": [
        {
          "url": "https://everquest.allakhazam.com/db/item.html?item=14303",
          "text": "Sheet Metal"
        },
        {
          "url": "https://everquest.allakhazam.com/db/item.html?item=107521",
          "text": "Sheet Metal"
        }
      ]
    },
    {
      "skill": "smithing",
      "name": "Tarnished Dagger",
      "candidates": [
        {
          "url": "https://everquest.allakhazam.com/db/item.html?item=62231",
          "text": "Tarnished Dagger"
        },
        {
          "url": "https://everquest.allakhazam.com/db/item.html?item=600",
          "text": "Tarnished Dagger"
        }
      ]
    },
    {
      "skill": "smithing",
      "name": "Tarnished Axe",
      "candidates": [
        {
          "url": "https://everquest.allakhazam.com/db/item.html?item=177",
          "text": "Tarnished Axe"
        },
        {
          "url": "https://everquest.allakhazam.com/db/item.html?item=60016",
          "text": "Tarnished Axe"
        }
      ]
    },
    {
      "skill": "smithing",
      "name": "Tarnished Long Sword",
      "candidates": [
        {
          "url": "https://everquest.allakhazam.com/db/item.html?item=183",
          "text": "Tarnished Long Sword"
        },
        {
          "url": "https://everquest.allakhazam.com/db/item.html?item=142607",
          "text": "Tarnished Long Sword"
        }
      ]
    },
    {
      "skill": "smithing",
      "name": "Buckler",
      "candidates": [
        {
          "url": "https://everquest.allakhazam.com/db/item.html?item=1076",
          "text": "Buckler [dropped]"
        },
        {
          "url": "https://everquest.allakhazam.com/db/item.html?item=1077",
          "text": "Buckler [crafted]"
        }
      ]
    },
    {
      "skill": "smithing",
      "name": "Targ Shield",
      "candidates": [
        {
          "url": "https://everquest.allakhazam.com/db/item.html?item=1081",
          "text": "Targ Shield"
        },
        {
          "url": "https://everquest.allakhazam.com/db/item.html?item=1086",
          "text": "Targ Shield [crafted]"
        }
      ]
    },
    {
      "skill": "smithing",
      "name": "Kite Shield",
      "candidates": [
        {
          "url": "https://everquest.allakhazam.com/db/item.html?item=1089",
          "text": "Kite Shield"
        },
        {
          "url": "https://everquest.allakhazam.com/db/item.html?item=49648",
          "text": "Kite Shield [crafted]"
        }
      ]
    },
    {
      "skill": "smithing",
      "name": "Round Shield",
      "candidates": [
        {
          "url": "https://everquest.allakhazam.com/db/item.html?item=1085",
          "text": "Round Shield [crafted]"
        },
        {
          "url": "https://everquest.allakhazam.com/db/item.html?item=1079",
          "text": "Round Shield"
        }
      ]
    },
    {
      "skill": "smithing",
      "name": "Tower Shield",
      "candidates": [
        {
          "url": "https://everquest.allakhazam.com/db/item.html?item=1097",
          "text": "Tower Shield"
        },
        {
          "url": "https://everquest.allakhazam.com/db/item.html?item=49151",
          "text": "Tower Shield [crafted]"
        }
      ]
    },
    {
      "skill": "smithing",
      "name": "Skirt",
      "candidates": [
        {
          "url": "https://everquest.allakhazam.com/db/item.html?item=82784",
          "text": "Skirt"
        },
        {
          "url": "https://everquest.allakhazam.com/db/item.html?item=71051",
          "text": "Skirt"
        }
      ]
    },
    {
      "skill": "fletching",
      "name": "CLASS 1 Wood Point Arrow",
      "candidates": [
        {
          "url": "https://everquest.allakhazam.com/db/item.html?item=23081",
          "text": "CLASS 1 Wood Point Arrow [Range 75]"
        },
        {
          "url": "https://everquest.allakhazam.com/db/item.html?item=23080",
          "text": "CLASS 1 Wood Point Arrow [Range 50]"
        },
        {
          "url": "https://everquest.allakhazam.com/db/item.html?item=23082",
          "text": "CLASS 1 Wood Point Arrow [Range 100]"
        }
      ]
    },
    {
      "skill": "fletching",
      "name": "CLASS 2 Wood Point Arrow",
      "candidates": [
        {
          "url": "https://everquest.allakhazam.com/db/item.html?item=25714",
          "text": "CLASS 2 Wood Point Arrow [Range 150]"
        },
        {
          "url": "https://everquest.allakhazam.com/db/item.html?item=25645",
          "text": "CLASS 2 Wood Point Arrow [Range 125]"
        },
        {
          "url": "https://everquest.allakhazam.com/db/item.html?item=25715",
          "text": "CLASS 2 Wood Point Arrow [Range 100]"
        }
      ]
    },
    {
      "skill": "fletching",
      "name": "CLASS 1 Bone Point Arrow",
      "candidates": [
        {
          "url": "https://everquest.allakhazam.com/db/item.html?item=23036",
          "text": "CLASS 1 Bone Point Arrow [Range 100]"
        },
        {
          "url": "https://everquest.allakhazam.com/db/item.html?item=23034",
          "text": "CLASS 1 Bone Point Arrow [Range 50]"
        },
        {
          "url": "https://everquest.allakhazam.com/db/item.html?item=23035",
          "text": "CLASS 1 Bone Point Arrow [Range 75]"
        }
      ]
    },
    {
      "skill": "fletching",
      "name": "CLASS 3 Bone Point Arrow",
      "candidates": [
        {
          "url": "https://everquest.allakhazam.com/db/item.html?item=30136",
          "text": "CLASS 3 Bone Point Arrow [small nock]"
        },
        {
          "url": "https://everquest.allakhazam.com/db/item.html?item=25646",
          "text": "CLASS 3 Bone Point Arrow [Range 5]"
        },
        {
          "url": "https://everquest.allakhazam.com/db/item.html?item=30135",
          "text": "CLASS 3 Bone Point Arrow [medium nock]"
        }
      ]
    },
    {
      "skill": "fletching",
      "name": "CLASS 2 Bone Point Arrow",
      "candidates": [
        {
          "url": "https://everquest.allakhazam.com/db/item.html?item=25641",
          "text": "CLASS 2 Bone Point Arrow [Range 100]"
        },
        {
          "url": "https://everquest.allakhazam.com/db/item.html?item=25640",
          "text": "CLASS 2 Bone Point Arrow [Range 125]"
        },
        {
          "url": "https://everquest.allakhazam.com/db/item.html?item=25642",
          "text": "CLASS 2 Bone Point Arrow [Range 150]"
        }
      ]
    },
    {
      "skill": "fletching",
      "name": "CLASS 1 Bone Hooked Arrow",
      "candidates": [
        {
          "url": "https://everquest.allakhazam.com/db/item.html?item=29474",
          "text": "CLASS 1 Bone Hooked Arrow [small nock]"
        },
        {
          "url": "https://everquest.allakhazam.com/db/item.html?item=29475",
          "text": "CLASS 1 Bone Hooked Arrow [medium nock]"
        },
        {
          "url": "https://everquest.allakhazam.com/db/item.html?item=29473",
          "text": "CLASS 1 Bone Hooked Arrow [large nock]"
        }
      ]
    },
    {
      "skill": "fletching",
      "name": "CLASS 3 Bone Hooked Arrow",
      "candidates": [
        {
          "url": "https://everquest.allakhazam.com/db/item.html?item=24072",
          "text": "CLASS 3 Bone Hooked Arrow [Range 50]"
        },
        {
          "url": "https://everquest.allakhazam.com/db/item.html?item=24073",
          "text": "CLASS 3 Bone Hooked Arrow [Range 5]"
        },
        {
          "url": "https://everquest.allakhazam.com/db/item.html?item=24074",
          "text": "CLASS 3 Bone Hooked Arrow [Range 25]"
        }
      ]
    },
    {
      "skill": "fletching",
      "name": "CLASS 2 Bone Hooked Arrow",
      "candidates": [
        {
          "url": "https://everquest.allakhazam.com/db/item.html?item=29900",
          "text": "CLASS 2 Bone Hooked Arrow [medium nock]"
        },
        {
          "url": "https://everquest.allakhazam.com/db/item.html?item=29899",
          "text": "CLASS 2 Bone Hooked Arrow [small nock]"
        },
        {
          "url": "https://everquest.allakhazam.com/db/item.html?item=29756",
          "text": "CLASS 2 Bone Hooked Arrow [large nock]"
        }
      ]
    },
    {
      "skill": "fletching",
      "name": "CLASS 4 Bone Hooked Arrow",
      "candidates": [
        {
          "url": "https://everquest.allakhazam.com/db/item.html?item=30358",
          "text": "CLASS 4 Bone Hooked Arrow [small nock]"
        },
        {
          "url": "https://everquest.allakhazam.com/db/item.html?item=30356",
          "text": "CLASS 4 Bone Hooked Arrow [large nock]"
        },
        {
          "url": "https://everquest.allakhazam.com/db/item.html?item=30357",
          "text": "CLASS 4 Bone Hooked Arrow [medium nock]"
        }
      ]
    },
    {
      "skill": "fletching",
      "name": "CLASS 2 Ceramic Hooked Arrow",
      "candidates": [
        {
          "url": "https://everquest.allakhazam.com/db/item.html?item=30028",
          "text": "CLASS 2 Ceramic Hooked Arrow [Range 125]"
        },
        {
          "url": "https://everquest.allakhazam.com/db/item.html?item=11437",
          "text": "CLASS 2 Ceramic Hooked Arrow [Range 150]"
        },
        {
          "url": "https://everquest.allakhazam.com/db/item.html?item=30027",
          "text": "CLASS 2 Ceramic Hooked Arrow [large nock]"
        }
      ]
    },
    {
      "skill": "fletching",
      "name": "CLASS 3 Ceramic Hooked Arrow",
      "candidates": [
        {
          "url": "https://everquest.allakhazam.com/db/item.html?item=30182",
          "text": "CLASS 3 Ceramic Hooked Arrow [large nock]"
        },
        {
          "url": "https://everquest.allakhazam.com/db/item.html?item=30183",
          "text": "CLASS 3 Ceramic Hooked Arrow [medium nock]"
        },
        {
          "url": "https://everquest.allakhazam.com/db/item.html?item=30184",
          "text": "CLASS 3 Ceramic Hooked Arrow [small nock]"
        }
      ]
    },
    {
      "skill": "fletching",
      "name": "CLASS 2 Ceramic Silver Tip Arrow",
      "candidates": [
        {
          "url": "https://everquest.allakhazam.com/db/item.html?item=17018",
          "text": "CLASS 2 Ceramic Silver Tip Arrow [Large Nock]"
        },
        {
          "url": "https://everquest.allakhazam.com/db/item.html?item=30032",
          "text": "CLASS 2 Ceramic Silver Tip Arrow [Medium Nock]"
        },
        {
          "url": "https://everquest.allakhazam.com/db/item.html?item=30033",
          "text": "CLASS 2 Ceramic Silver Tip Arrow [Small Nock]"
        }
      ]
    },
    {
      "skill": "fletching",
      "name": "CLASS 4 Ceramic Hooked Arrow",
      "candidates": [
        {
          "url": "https://everquest.allakhazam.com/db/item.html?item=30571",
          "text": "CLASS 4 Ceramic Hooked Arrow [medium nock]"
        },
        {
          "url": "https://everquest.allakhazam.com/db/item.html?item=30572",
          "text": "CLASS 4 Ceramic Hooked Arrow [small nock]"
        },
        {
          "url": "https://everquest.allakhazam.com/db/item.html?item=30382",
          "text": "CLASS 4 Ceramic Hooked Arrow [large nock]"
        }
      ]
    },
    {
      "skill": "fletching",
      "name": "CLASS 5 Ceramic Silver Tip Arrow",
      "candidates": [
        {
          "url": "https://everquest.allakhazam.com/db/item.html?item=31147",
          "text": "CLASS 5 Ceramic Silver Tip Arrow [large nock]"
        },
        {
          "url": "https://everquest.allakhazam.com/db/item.html?item=31150",
          "text": "CLASS 5 Ceramic Silver Tip Arrow [medium nock]"
        },
        {
          "url": "https://everquest.allakhazam.com/db/item.html?item=31153",
          "text": "CLASS 5 Ceramic Silver Tip Arrow [small nock]"
        }
      ]
    },
    {
      "skill": "fletching",
      "name": "CLASS 3 Ceramic Silver Tip Arrow",
      "candidates": [
        {
          "url": "https://everquest.allakhazam.com/db/item.html?item=30192",
          "text": "CLASS 3 Ceramic Silver Tip Arrow [medium nock]"
        },
        {
          "url": "https://everquest.allakhazam.com/db/item.html?item=30191",
          "text": "CLASS 3 Ceramic Silver Tip Arrow [large nock]"
        },
        {
          "url": "https://everquest.allakhazam.com/db/item.html?item=30193",
          "text": "CLASS 3 Ceramic Silver Tip Arrow [small nock]"
        }
      ]
    },
    {
      "skill": "fletching",
      "name": "CLASS 2 Steel Silver Tip Arrow",
      "candidates": [
        {
          "url": "https://everquest.allakhazam.com/db/item.html?item=27464",
          "text": "CLASS 2 Steel Silver Tip Arrow [Range 125]"
        },
        {
          "url": "https://everquest.allakhazam.com/db/item.html?item=26807",
          "text": "CLASS 2 Steel Silver Tip Arrow [Range 100]"
        },
        {
          "url": "https://everquest.allakhazam.com/db/item.html?item=27463",
          "text": "CLASS 2 Steel Silver Tip Arrow [Range 150]"
        }
      ]
    },
    {
      "skill": "fletching",
      "name": "CLASS 3 Steel Silver Tip Arrow",
      "candidates": [
        {
          "url": "https://everquest.allakhazam.com/db/item.html?item=30284",
          "text": "CLASS 3 Steel Silver Tip Arrow [Range 50]"
        },
        {
          "url": "https://everquest.allakhazam.com/db/item.html?item=30282",
          "text": "CLASS 3 Steel Silver Tip Arrow [Range 5]"
        },
        {
          "url": "https://everquest.allakhazam.com/db/item.html?item=30283",
          "text": "CLASS 3 Steel Silver Tip Arrow [Range 25]"
        }
      ]
    },
    {
      "skill": "fletching",
      "name": "CLASS 4 Ceramic Silver Tip Arrow",
      "candidates": [
        {
          "url": "https://everquest.allakhazam.com/db/item.html?item=30576",
          "text": "CLASS 4 Ceramic Silver Tip Arrow [large nock]"
        },
        {
          "url": "https://everquest.allakhazam.com/db/item.html?item=30577",
          "text": "CLASS 4 Ceramic Silver Tip Arrow [medium nock]"
        },
        {
          "url": "https://everquest.allakhazam.com/db/item.html?item=30578",
          "text": "CLASS 4 Ceramic Silver Tip Arrow [small nock]"
        }
      ]
    },
    {
      "skill": "fletching",
      "name": "CLASS 4 Steel Silver Tip Arrow",
      "candidates": [
        {
          "url": "https://everquest.allakhazam.com/db/item.html?item=30945",
          "text": "CLASS 4 Steel Silver Tip Arrow [large nock]"
        },
        {
          "url": "https://everquest.allakhazam.com/db/item.html?item=30952",
          "text": "CLASS 4 Steel Silver Tip Arrow [small nock]"
        },
        {
          "url": "https://everquest.allakhazam.com/db/item.html?item=30948",
          "text": "CLASS 4 Steel Silver Tip Arrow [medium nock]"
        }
      ]
    },
    {
      "skill": "fletching",
      "name": "CLASS 5 Steel Silver Tip Arrow",
      "candidates": [
        {
          "url": "https://everquest.allakhazam.com/db/item.html?item=31164",
          "text": "CLASS 5 Steel Silver Tip Arrow [medium nock]"
        },
        {
          "url": "https://everquest.allakhazam.com/db/item.html?item=31163",
          "text": "CLASS 5 Steel Silver Tip Arrow [large nock]"
        },
        {
          "url": "https://everquest.allakhazam.com/db/item.html?item=31165",
          "text": "CLASS 5 Steel Silver Tip Arrow [small nock]"
        }
      ]
    },
    {
      "skill": "fletching",
      "name": "CLASS 6 Ceramic Silver Tip Arrow",
      "candidates": [
        {
          "url": "https://everquest.allakhazam.com/db/item.html?item=31560",
          "text": "CLASS 6 Ceramic Silver Tip Arrow [small nock]"
        },
        {
          "url": "https://everquest.allakhazam.com/db/item.html?item=31558",
          "text": "CLASS 6 Ceramic Silver Tip Arrow [large nock]"
        },
        {
          "url": "https://everquest.allakhazam.com/db/item.html?item=31559",
          "text": "CLASS 6 Ceramic Silver Tip Arrow [medium nock]"
        }
      ]
    },
    {
      "skill": "fletching",
      "name": "CLASS 6 Steel Silver Tip Arrow",
      "candidates": [
        {
          "url": "https://everquest.allakhazam.com/db/item.html?item=31571",
          "text": "CLASS 6 Steel Silver Tip Arrow [large nock]"
        },
        {
          "url": "https://everquest.allakhazam.com/db/item.html?item=31572",
          "text": "CLASS 6 Steel Silver Tip Arrow [medium nock]"
        },
        {
          "url": "https://everquest.allakhazam.com/db/item.html?item=31573",
          "text": "CLASS 6 Steel Silver Tip Arrow [Range 100]"
        }
      ]
    },
    {
      "skill": "pottery",
      "name": "Mixing Bowl",
      "candidates": [
        {
          "url": "https://everquest.allakhazam.com/db/item.html?item=12292",
          "text": "Mixing Bowl"
        },
        {
          "url": "https://everquest.allakhazam.com/db/item.html?item=94820",
          "text": "Mixing Bowl [placeable]"
        },
        {
          "url": "https://everquest.allakhazam.com/db/item.html?item=123564",
          "text": "Mixing Bowl [Early Prog Servers]"
        }
      ]
    },
    {
      "skill": "pottery",
      "name": "Unfired Idol",
      "candidates": [
        {
          "url": "https://everquest.allakhazam.com/db/item.html?item=28556",
          "text": "Unfired Idol [Idol of Quellious]"
        },
        {
          "url": "https://everquest.allakhazam.com/db/item.html?item=28550",
          "text": "Unfired Idol [Idol of Erollisi Marr]"
        },
        {
          "url": "https://everquest.allakhazam.com/db/item.html?item=28558",
          "text": "Unfired Idol [Idol Of Rodcet Nife]"
        },
        {
          "url": "https://everquest.allakhazam.com/db/item.html?item=28559",
          "text": "Unfired Idol [Idol of Solusek Ro]"
        },
        {
          "url": "https://everquest.allakhazam.com/db/item.html?item=80150",
          "text": "Unfired Idol [Idol of Prexus]"
        },
        {
          "url": "https://everquest.allakhazam.com/db/item.html?item=28561",
          "text": "Unfired Idol [Idol of Tunare]"
        },
        {
          "url": "https://everquest.allakhazam.com/db/item.html?item=28557",
          "text": "Unfired Idol [Idol Of Rallos Zek]"
        },
        {
          "url": "https://everquest.allakhazam.com/db/item.html?item=28555",
          "text": "Unfired Idol [Idol of Mithaniel Marr]"
        },
        {
          "url": "https://everquest.allakhazam.com/db/item.html?item=28548",
          "text": "Unfired Idol [Idol Of Brell Serilis]"
        },
        {
          "url": "https://everquest.allakhazam.com/db/item.html?item=28560",
          "text": "Unfired Idol [Idol Of The Tribunal]"
        },
        {
          "url": "https://everquest.allakhazam.com/db/item.html?item=28552",
          "text": "Unfired Idol [Idol Of Innoruuk]"
        },
        {
          "url": "https://everquest.allakhazam.com/db/item.html?item=28551",
          "text": "Unfired Idol [Idol of Bristlebane]"
        },
        {
          "url": "https://everquest.allakhazam.com/db/item.html?item=28549",
          "text": "Unfired Idol [Idol of Cazic Thule]"
        },
        {
          "url": "https://everquest.allakhazam.com/db/item.html?item=76394",
          "text": "Unfired Idol [Idol of Bertoxxulous]"
        },
        {
          "url": "https://everquest.allakhazam.com/db/item.html?item=28553",
          "text": "Unfired Idol [Idol Of Karana]"
        }
      ]
    },
    {
      "skill": "tailoring",
      "name": "Crystalline Silk Mask",
      "candidates": [
        {
          "url": "https://everquest.allakhazam.com/db/item.html?item=4121",
          "text": "Crystalline Silk Mask [dropped]"
        },
        {
          "url": "https://everquest.allakhazam.com/db/item.html?item=5162",
          "text": "Crystalline Silk Mask"
        }
      ]
    },
    {
      "skill": "tinkering",
      "name": "Gnomish Firework",
      "candidates": [
        {
          "url": "https://everquest.allakhazam.com/db/item.html?item=3643",
          "text": "Gnomish Firework [Happy Panda]"
        },
        {
          "url": "https://everquest.allakhazam.com/db/item.html?item=27361",
          "text": "Gnomish Firework [Ground Bloom Flower]"
        },
        {
          "url": "https://everquest.allakhazam.com/db/item.html?item=27360",
          "text": "Gnomish Firework [Angry Bee]"
        },
        {
          "url": "https://everquest.allakhazam.com/db/item.html?item=27359",
          "text": "Gnomish Firework [Blazing Comet]"
        }
      ]
    },
    {
      "skill": "tinkering",
      "name": "Compass",
      "candidates": [
        {
          "url": "https://everquest.allakhazam.com/db/item.html?item=148200",
          "text": "Compass"
        },
        {
          "url": "https://everquest.allakhazam.com/db/item.html?item=2344",
          "text": "Compass"
        }
      ]
    },
    {
      "skill": "tinkering",
      "name": "Spyglass",
      "candidates": [
        {
          "url": "https://everquest.allakhazam.com/db/item.html?item=97775",
          "text": "Spyglass"
        },
        {
          "url": "https://everquest.allakhazam.com/db/item.html?item=6166",
          "text": "Spyglass"
        }
      ]
    },
    {
      "skill": "brewing",
      "name": "Water Flask",
      "candidates": [
        {
          "url": "https://everquest.allakhazam.com/db/item.html?item=7773",
          "text": "Water Flask"
        },
        {
          "url": "https://everquest.allakhazam.com/db/item.html?item=59571",
          "text": "Water Flask"
        }
      ]
    }
  ],
  "skippedProcessComponents": [
    "Animal Template",
    "Axe Head Mold",
    "Barbarian Template",
    "Block of Clay",
    "Bowl Sketch",
    "Bread Tin Mold",
    "Buckler Mold",
    "Cake Round Mold",
    "Cake Round Sketch",
    "Ceramic Lining Sketch",
    "Container Base Mold",
    "Container Lid Mold",
    "Curved Blade Mold",
    "Dagger Blade Mold",
    "Dual-Edged Blade Mold",
    "Fer`Esh Blade Mold",
    "File Mold",
    "Firing Sheet",
    "Gnome Template",
    "Halberd Head Mold",
    "Hammer Head Mold",
    "Heavy Steel Blade Mold",
    "High Quality Firing Sheet",
    "Hilt Mold",
    "Hinge Mold",
    "Idol Sketch",
    "Javelin Mold",
    "Kite Shield Mold",
    "Lantern Casing Mold",
    "Large Block of Clay",
    "Large Bowl Sketch",
    "Large Container Base Mold",
    "Large Container Lid Mold",
    "Large Jar Sketch",
    "Lined Vial Sketch",
    "Lockpick Mold",
    "Long Blade Mold",
    "Mace Head Mold",
    "Medium Bowl Sketch",
    "Medium Jar Sketch",
    "Muffin Tin Mold",
    "Muffin Tin Sketch",
    "Needle Mold",
    "Pick Head Mold",
    "Pie Tin Mold",
    "Pie Tin Sketch",
    "Pommel Mold",
    "Pot Mold",
    "Pot Sketch",
    "Quality Firing Sheet",
    "Round Shield Mold",
    "Scaler Mold",
    "Sealed Vial Sketch",
    "Shan`Tok Blade Mold",
    "Shaped Mold",
    "Sheer Blade Mold",
    "Short Blade Mold",
    "Shuriken Mold",
    "Skewer Mold",
    "Skewers Sketch",
    "Small Block of Clay",
    "Small Container Base Mold",
    "Small Container Lid Mold",
    "Small Deity Sketch",
    "Small Jar Sketch",
    "Smoke Base Mold",
    "Smoker Sketch",
    "Smoker Support Mold",
    "Spear Head Mold",
    "Spiked Ball Mold",
    "Standing Legs Mold",
    "Targ Shield Mold",
    "Thimble Mold",
    "Thin Blade Mold",
    "Throwing Axe Mold",
    "Throwing Knife Mold",
    "Toolbox Mold",
    "Tower Shield Mold",
    "Troll Template",
    "Unfired Idol",
    "Vial Sketch"
  ],
  "skippedEraSensitiveItems": [
    {
      "skill": "pottery",
      "name": "Idol of Bertoxxulous",
      "reason": "Pottery idol stats are sourced from P99 shorthand; Allakhazam fallback may match live-era items with inflated stats."
    },
    {
      "skill": "pottery",
      "name": "Idol of Brell Serilis",
      "reason": "Pottery idol stats are sourced from P99 shorthand; Allakhazam fallback may match live-era items with inflated stats."
    },
    {
      "skill": "pottery",
      "name": "Idol of Cazic Thule",
      "reason": "Pottery idol stats are sourced from P99 shorthand; Allakhazam fallback may match live-era items with inflated stats."
    },
    {
      "skill": "pottery",
      "name": "Idol of Erollisi Marr",
      "reason": "Pottery idol stats are sourced from P99 shorthand; Allakhazam fallback may match live-era items with inflated stats."
    },
    {
      "skill": "pottery",
      "name": "Idol of Fizzlethorpe Bristlebane",
      "reason": "Pottery idol stats are sourced from P99 shorthand; Allakhazam fallback may match live-era items with inflated stats."
    },
    {
      "skill": "pottery",
      "name": "Idol of Innoruuk",
      "reason": "Pottery idol stats are sourced from P99 shorthand; Allakhazam fallback may match live-era items with inflated stats."
    },
    {
      "skill": "pottery",
      "name": "Idol of Karana",
      "reason": "Pottery idol stats are sourced from P99 shorthand; Allakhazam fallback may match live-era items with inflated stats."
    },
    {
      "skill": "pottery",
      "name": "Idol of Mithaniel Marr",
      "reason": "Pottery idol stats are sourced from P99 shorthand; Allakhazam fallback may match live-era items with inflated stats."
    },
    {
      "skill": "pottery",
      "name": "Idol of Prexus",
      "reason": "Pottery idol stats are sourced from P99 shorthand; Allakhazam fallback may match live-era items with inflated stats."
    },
    {
      "skill": "pottery",
      "name": "Idol of Quellious",
      "reason": "Pottery idol stats are sourced from P99 shorthand; Allakhazam fallback may match live-era items with inflated stats."
    },
    {
      "skill": "pottery",
      "name": "Idol of Rallos Zek",
      "reason": "Pottery idol stats are sourced from P99 shorthand; Allakhazam fallback may match live-era items with inflated stats."
    },
    {
      "skill": "pottery",
      "name": "Idol of Rodcet Nife",
      "reason": "Pottery idol stats are sourced from P99 shorthand; Allakhazam fallback may match live-era items with inflated stats."
    },
    {
      "skill": "pottery",
      "name": "Idol of Solusek Ro",
      "reason": "Pottery idol stats are sourced from P99 shorthand; Allakhazam fallback may match live-era items with inflated stats."
    },
    {
      "skill": "pottery",
      "name": "Idol of the Tribunal",
      "reason": "Pottery idol stats are sourced from P99 shorthand; Allakhazam fallback may match live-era items with inflated stats."
    },
    {
      "skill": "pottery",
      "name": "Idol of Tunare",
      "reason": "Pottery idol stats are sourced from P99 shorthand; Allakhazam fallback may match live-era items with inflated stats."
    }
  ]
}
