{
  "source": "https://wiki.project1999.com/Velious_Class_Armor",
  "armorPages": 42,
  "discoveredRewards": 336,
  "processedRewards": 336,
  "imported": [
    {
      "item": "Firebrand's Boots",
      "itemId": "32974",
      "armorSet": "Kael",
      "classCode": "BER",
      "sourceUrl": "https://everquest.allakhazam.com/db/item.html?item=32974",
      "icon": "https://everquest.allakhazam.com/pgfx/item_545.png"
    },
    {
      "item": "Firebrand's Bracer",
      "itemId": "32973",
      "armorSet": "Kael",
      "classCode": "BER",
      "sourceUrl": "https://everquest.allakhazam.com/db/item.html?item=32973",
      "icon": "https://everquest.allakhazam.com/pgfx/item_620.png"
    },
    {
      "item": "Firebrand's Coif",
      "itemId": "57128",
      "armorSet": "Kael",
      "classCode": "BER",
      "sourceUrl": "https://everquest.allakhazam.com/db/item.html?item=57128",
      "icon": "https://everquest.allakhazam.com/pgfx/item_625.png"
    },
    {
      "item": "Firebrand's Gauntlets",
      "itemId": "57129",
      "armorSet": "Kael",
      "classCode": "BER",
      "sourceUrl": "https://everquest.allakhazam.com/db/item.html?item=57129",
      "icon": "https://everquest.allakhazam.com/pgfx/item_526.png"
    },
    {
      "item": "Firebrand's Leggings",
      "itemId": "26689",
      "armorSet": "Kael",
      "classCode": "BER",
      "sourceUrl": "https://everquest.allakhazam.com/db/item.html?item=26689",
      "icon": "https://everquest.allakhazam.com/pgfx/item_630.png"
    },
    {
      "item": "Firebrand's Sleeves",
      "itemId": "33657",
      "armorSet": "Kael",
      "classCode": "BER",
      "sourceUrl": "https://everquest.allakhazam.com/db/item.html?item=33657",
      "icon": "https://everquest.allakhazam.com/pgfx/item_669.png"
    },
    {
      "item": "Firebrand's Tunic",
      "itemId": "26688",
      "armorSet": "Kael",
      "classCode": "BER",
      "sourceUrl": "https://everquest.allakhazam.com/db/item.html?item=26688",
      "icon": "https://everquest.allakhazam.com/pgfx/item_538.png"
    },
    {
      "item": "Boots of Fire's Fury",
      "itemId": "32815",
      "armorSet": "Skyshrine",
      "classCode": "BER",
      "sourceUrl": "https://everquest.allakhazam.com/db/item.html?item=32815",
      "icon": "https://everquest.allakhazam.com/pgfx/item_524.png"
    },
    {
      "item": "Bracer of Fire's Fury",
      "itemId": "30332",
      "armorSet": "Skyshrine",
      "classCode": "BER",
      "sourceUrl": "https://everquest.allakhazam.com/db/item.html?item=30332",
      "icon": "https://everquest.allakhazam.com/pgfx/item_516.png"
    },
    {
      "item": "Coif of Fire's Fury",
      "itemId": "32814",
      "armorSet": "Skyshrine",
      "classCode": "BER",
      "sourceUrl": "https://everquest.allakhazam.com/db/item.html?item=32814",
      "icon": "https://everquest.allakhazam.com/pgfx/item_625.png"
    },
    {
      "item": "Gauntlets of Fire's Fury",
      "itemId": "30333",
      "armorSet": "Skyshrine",
      "classCode": "BER",
      "sourceUrl": "https://everquest.allakhazam.com/db/item.html?item=30333",
      "icon": "https://everquest.allakhazam.com/pgfx/item_531.png"
    },
    {
      "item": "Leggings of Fire's Fury",
      "itemId": "30334",
      "armorSet": "Skyshrine",
      "classCode": "BER",
      "sourceUrl": "https://everquest.allakhazam.com/db/item.html?item=30334",
      "icon": "https://everquest.allakhazam.com/pgfx/item_540.png"
    },
    {
      "item": "Sleeves of Fire's Fury",
      "itemId": "50240",
      "armorSet": "Skyshrine",
      "classCode": "BER",
      "sourceUrl": "https://everquest.allakhazam.com/db/item.html?item=50240",
      "icon": "https://everquest.allakhazam.com/pgfx/item_622.png"
    },
    {
      "item": "Tunic of Fire's Fury",
      "itemId": "26829",
      "armorSet": "Skyshrine",
      "classCode": "BER",
      "sourceUrl": "https://everquest.allakhazam.com/db/item.html?item=26829",
      "icon": "https://everquest.allakhazam.com/pgfx/item_538.png"
    },
    {
      "item": "Icefury Boots",
      "itemId": "26701",
      "armorSet": "Thurgadin",
      "classCode": "BER",
      "sourceUrl": "https://everquest.allakhazam.com/db/item.html?item=26701",
      "icon": "https://everquest.allakhazam.com/pgfx/item_524.png"
    },
    {
      "item": "Icefury Bracer",
      "itemId": "26516",
      "armorSet": "Thurgadin",
      "classCode": "BER",
      "sourceUrl": "https://everquest.allakhazam.com/db/item.html?item=26516",
      "icon": "https://everquest.allakhazam.com/pgfx/item_516.png"
    },
    {
      "item": "Icefury Coif",
      "itemId": "29787",
      "armorSet": "Thurgadin",
      "classCode": "BER",
      "sourceUrl": "https://everquest.allakhazam.com/db/item.html?item=29787",
      "icon": "https://everquest.allakhazam.com/pgfx/item_625.png"
    },
    {
      "item": "Icefury Gauntlets",
      "itemId": "26703",
      "armorSet": "Thurgadin",
      "classCode": "BER",
      "sourceUrl": "https://everquest.allakhazam.com/db/item.html?item=26703",
      "icon": "https://everquest.allakhazam.com/pgfx/item_531.png"
    },
    {
      "item": "Icefury Greaves",
      "itemId": "26702",
      "armorSet": "Thurgadin",
      "classCode": "BER",
      "sourceUrl": "https://everquest.allakhazam.com/db/item.html?item=26702",
      "icon": "https://everquest.allakhazam.com/pgfx/item_540.png"
    },
    {
      "item": "Icefury Sleeves",
      "itemId": "26518",
      "armorSet": "Thurgadin",
      "classCode": "BER",
      "sourceUrl": "https://everquest.allakhazam.com/db/item.html?item=26518",
      "icon": "https://everquest.allakhazam.com/pgfx/item_622.png"
    },
    {
      "item": "Icefury Tunic",
      "itemId": "26517",
      "armorSet": "Thurgadin",
      "classCode": "BER",
      "sourceUrl": "https://everquest.allakhazam.com/db/item.html?item=26517",
      "icon": "https://everquest.allakhazam.com/pgfx/item_538.png"
    },
    {
      "item": "Armband of Beast Mastery",
      "itemId": "11619",
      "armorSet": "Kael",
      "classCode": "BST",
      "sourceUrl": "https://everquest.allakhazam.com/db/item.html?item=11619",
      "icon": "https://everquest.allakhazam.com/pgfx/item_634.png"
    },
    {
      "item": "Boots of Beast Mastery",
      "itemId": "11617",
      "armorSet": "Kael",
      "classCode": "BST",
      "sourceUrl": "https://everquest.allakhazam.com/db/item.html?item=11617",
      "icon": "https://everquest.allakhazam.com/pgfx/item_633.png"
    },
    {
      "item": "Bracer of Beast Mastery",
      "itemId": "11618",
      "armorSet": "Kael",
      "classCode": "BST",
      "sourceUrl": "https://everquest.allakhazam.com/db/item.html?item=11618",
      "icon": "https://everquest.allakhazam.com/pgfx/item_637.png"
    },
    {
      "item": "Chestguard of Beast Mastery",
      "itemId": "14114",
      "armorSet": "Kael",
      "classCode": "BST",
      "sourceUrl": "https://everquest.allakhazam.com/db/item.html?item=14114",
      "icon": "https://everquest.allakhazam.com/pgfx/item_632.png"
    },
    {
      "item": "Crown of Beast Mastery",
      "itemId": "13260",
      "armorSet": "Kael",
      "classCode": "BST",
      "sourceUrl": "https://everquest.allakhazam.com/db/item.html?item=13260",
      "icon": "https://everquest.allakhazam.com/pgfx/item_640.png"
    },
    {
      "item": "Gloves of Beast Mastery",
      "itemId": "15969",
      "armorSet": "Kael",
      "classCode": "BST",
      "sourceUrl": "https://everquest.allakhazam.com/db/item.html?item=15969",
      "icon": "https://everquest.allakhazam.com/pgfx/item_636.png"
    },
    {
      "item": "Leggings of Beast Mastery",
      "itemId": "15970",
      "armorSet": "Kael",
      "classCode": "BST",
      "sourceUrl": "https://everquest.allakhazam.com/db/item.html?item=15970",
      "icon": "https://everquest.allakhazam.com/pgfx/item_635.png"
    },
    {
      "item": "Savage Armband",
      "itemId": "8791",
      "armorSet": "Skyshrine",
      "classCode": "BST",
      "sourceUrl": "https://everquest.allakhazam.com/db/item.html?item=8791",
      "icon": "https://everquest.allakhazam.com/pgfx/item_634.png"
    },
    {
      "item": "Savage Boots",
      "itemId": "8792",
      "armorSet": "Skyshrine",
      "classCode": "BST",
      "sourceUrl": "https://everquest.allakhazam.com/db/item.html?item=8792",
      "icon": "https://everquest.allakhazam.com/pgfx/item_633.png"
    },
    {
      "item": "Savage Bracer",
      "itemId": "8793",
      "armorSet": "Skyshrine",
      "classCode": "BST",
      "sourceUrl": "https://everquest.allakhazam.com/db/item.html?item=8793",
      "icon": "https://everquest.allakhazam.com/pgfx/item_637.png"
    },
    {
      "item": "Savage Chestguard",
      "itemId": "11658",
      "armorSet": "Skyshrine",
      "classCode": "BST",
      "sourceUrl": "https://everquest.allakhazam.com/db/item.html?item=11658",
      "icon": "https://everquest.allakhazam.com/pgfx/item_632.png"
    },
    {
      "item": "Savage Gloves",
      "itemId": "8794",
      "armorSet": "Skyshrine",
      "classCode": "BST",
      "sourceUrl": "https://everquest.allakhazam.com/db/item.html?item=8794",
      "icon": "https://everquest.allakhazam.com/pgfx/item_636.png"
    },
    {
      "item": "Savage Helm",
      "itemId": "8795",
      "armorSet": "Skyshrine",
      "classCode": "BST",
      "sourceUrl": "https://everquest.allakhazam.com/db/item.html?item=8795",
      "icon": "https://everquest.allakhazam.com/pgfx/item_640.png"
    },
    {
      "item": "Savage Leggings",
      "itemId": "8790",
      "armorSet": "Skyshrine",
      "classCode": "BST",
      "sourceUrl": "https://everquest.allakhazam.com/db/item.html?item=8790",
      "icon": "https://everquest.allakhazam.com/pgfx/item_635.png"
    }
  ],
  "mergedExisting": [
    {
      "item": "Troubadour's Boots",
      "key": "Troubadour's Boots",
      "itemId": "5101",
      "armorSet": "Kael",
      "classCode": "BRD"
    },
    {
      "item": "Troubadour's Bracer",
      "key": "Troubadour's Bracer",
      "itemId": "5176",
      "armorSet": "Kael",
      "classCode": "BRD"
    },
    {
      "item": "Troubadour's Breastplate",
      "key": "Troubadour's Breastplate",
      "itemId": "6223",
      "armorSet": "Kael",
      "classCode": "BRD"
    },
    {
      "item": "Troubadour's Gauntlets",
      "key": "Troubadour's Gauntlets",
      "itemId": "5318",
      "armorSet": "Kael",
      "classCode": "BRD"
    },
    {
      "item": "Troubadour's Greaves",
      "key": "Troubadour's Greaves",
      "itemId": "5150",
      "armorSet": "Kael",
      "classCode": "BRD"
    },
    {
      "item": "Troubadour's Helm",
      "key": "Troubadour's Helm",
      "itemId": "6222",
      "armorSet": "Kael",
      "classCode": "BRD"
    },
    {
      "item": "Troubadour's Vambraces",
      "key": "Troubadour's Vambraces",
      "itemId": "5125",
      "armorSet": "Kael",
      "classCode": "BRD"
    },
    {
      "item": "Boots of Twilight",
      "key": "Boots of Twilight",
      "itemId": "5978",
      "armorSet": "Skyshrine",
      "classCode": "BRD"
    },
    {
      "item": "Bracer of Twilight",
      "key": "Bracer of Twilight",
      "itemId": "5824",
      "armorSet": "Skyshrine",
      "classCode": "BRD"
    },
    {
      "item": "Breastplate of Twilight",
      "key": "Breastplate of Twilight",
      "itemId": "5648",
      "armorSet": "Skyshrine",
      "classCode": "BRD"
    },
    {
      "item": "Gauntlets of Twilight",
      "key": "Gauntlets of Twilight",
      "itemId": "5596",
      "armorSet": "Skyshrine",
      "classCode": "BRD"
    },
    {
      "item": "Greaves of Twilight",
      "key": "Greaves of Twilight",
      "itemId": "5615",
      "armorSet": "Skyshrine",
      "classCode": "BRD"
    },
    {
      "item": "Helm of Twilight",
      "key": "Helm of Twilight",
      "itemId": "5979",
      "armorSet": "Skyshrine",
      "classCode": "BRD"
    },
    {
      "item": "Vambraces of Twilight",
      "key": "Vambraces of Twilight",
      "itemId": "5649",
      "armorSet": "Skyshrine",
      "classCode": "BRD"
    },
    {
      "item": "Resonant Boots",
      "key": "Resonant Boots",
      "itemId": "4574",
      "armorSet": "Thurgadin",
      "classCode": "BRD"
    },
    {
      "item": "Resonant Bracer",
      "key": "Resonant Bracer",
      "itemId": "4667",
      "armorSet": "Thurgadin",
      "classCode": "BRD"
    },
    {
      "item": "Resonant Breastplate",
      "key": "Resonant Breastplate",
      "itemId": "4967",
      "armorSet": "Thurgadin",
      "classCode": "BRD"
    },
    {
      "item": "Resonant Gauntlets",
      "key": "Resonant Gauntlets",
      "itemId": "5279",
      "armorSet": "Thurgadin",
      "classCode": "BRD"
    },
    {
      "item": "Resonant Greaves",
      "key": "Resonant Greaves",
      "itemId": "4897",
      "armorSet": "Thurgadin",
      "classCode": "BRD"
    },
    {
      "item": "Resonant Helm",
      "key": "Resonant Helm",
      "itemId": "4749",
      "armorSet": "Thurgadin",
      "classCode": "BRD"
    },
    {
      "item": "Resonant Vambraces",
      "key": "Resonant Vambraces",
      "itemId": "4673",
      "armorSet": "Thurgadin",
      "classCode": "BRD"
    },
    {
      "item": "Armband of the Beastlord",
      "key": "Armband of the Beastlord",
      "itemId": "10149",
      "armorSet": "Thurgadin",
      "classCode": "BST"
    },
    {
      "item": "Boots of the Beastlord",
      "key": "Boots of the Beastlord",
      "itemId": "10334",
      "armorSet": "Thurgadin",
      "classCode": "BST"
    },
    {
      "item": "Bracer of the Beastlord",
      "key": "Bracer of the Beastlord",
      "itemId": "10576",
      "armorSet": "Thurgadin",
      "classCode": "BST"
    },
    {
      "item": "Chestguard of the Beastlord",
      "key": "Chestguard of the Beastlord",
      "itemId": "13145",
      "armorSet": "Thurgadin",
      "classCode": "BST"
    },
    {
      "item": "Crown of the Beastlord",
      "key": "Crown of the Beastlord",
      "itemId": "9009",
      "armorSet": "Thurgadin",
      "classCode": "BST"
    },
    {
      "item": "Gloves of the Beastlord",
      "key": "Gloves of the Beastlord",
      "itemId": "11384",
      "armorSet": "Thurgadin",
      "classCode": "BST"
    },
    {
      "item": "Leggings of the Beastlord",
      "key": "Leggings of the Beastlord",
      "itemId": "8884",
      "armorSet": "Thurgadin",
      "classCode": "BST"
    },
    {
      "item": "Templar's Boots",
      "key": "Templar's Boots",
      "itemId": "5127",
      "armorSet": "Kael",
      "classCode": "CLR"
    },
    {
      "item": "Templar's Bracer",
      "key": "Templar's Bracer",
      "itemId": "5126",
      "armorSet": "Kael",
      "classCode": "CLR"
    },
    {
      "item": "Templar's Chestplate",
      "key": "Templar's Chestplate",
      "itemId": "4952",
      "armorSet": "Kael",
      "classCode": "CLR"
    },
    {
      "item": "Templar's Crown",
      "key": "Templar's Crown",
      "itemId": "5168",
      "armorSet": "Kael",
      "classCode": "CLR"
    },
    {
      "item": "Templar's Gauntlets",
      "key": "Templar's Gauntlets",
      "itemId": "4859",
      "armorSet": "Kael",
      "classCode": "CLR"
    },
    {
      "item": "Templar's Leggings",
      "key": "Templar's Leggings",
      "itemId": "4983",
      "armorSet": "Kael",
      "classCode": "CLR"
    },
    {
      "item": "Templar's Vambraces",
      "key": "Templar's Vambraces",
      "itemId": "5088",
      "armorSet": "Kael",
      "classCode": "CLR"
    },
    {
      "item": "Akkirus' Boots of the Risen",
      "key": "Akkirus' Boots of the Risen",
      "itemId": "5385",
      "armorSet": "Skyshrine",
      "classCode": "CLR"
    },
    {
      "item": "Akkirus' Bracelet of the Risen",
      "key": "Akkirus' Bracelet of the Risen",
      "itemId": "5154",
      "armorSet": "Skyshrine",
      "classCode": "CLR"
    },
    {
      "item": "Akkirus' Chestplate of the Risen",
      "key": "Akkirus' Chestplate of the Risen",
      "itemId": "5352",
      "armorSet": "Skyshrine",
      "classCode": "CLR"
    },
    {
      "item": "Akkirus' Crown of the Risen",
      "key": "Akkirus' Crown of the Risen",
      "itemId": "5135",
      "armorSet": "Skyshrine",
      "classCode": "CLR"
    },
    {
      "item": "Akkirus' Gauntlets of the Risen",
      "key": "Akkirus' Gauntlets of the Risen",
      "itemId": "5504",
      "armorSet": "Skyshrine",
      "classCode": "CLR"
    },
    {
      "item": "Akkirus' Greaves of the Risen",
      "key": "Akkirus' Greaves of the Risen",
      "itemId": "5079",
      "armorSet": "Skyshrine",
      "classCode": "CLR"
    },
    {
      "item": "Akkirus' Vambraces of the Risen",
      "key": "Akkirus' Vambraces of the Risen",
      "itemId": "5390",
      "armorSet": "Skyshrine",
      "classCode": "CLR"
    },
    {
      "item": "Boots of Forbidden Rites",
      "key": "Boots of Forbidden Rites",
      "itemId": "4511",
      "armorSet": "Thurgadin",
      "classCode": "CLR"
    },
    {
      "item": "Bracers of Forbidden Rites",
      "key": "Bracers of Forbidden Rites",
      "itemId": "4336",
      "armorSet": "Thurgadin",
      "classCode": "CLR"
    },
    {
      "item": "Breastplate of Forbidden Rites",
      "key": "Breastplate of Forbidden Rites",
      "itemId": "4954",
      "armorSet": "Thurgadin",
      "classCode": "CLR"
    },
    {
      "item": "Crown of Forbidden Rites",
      "key": "Crown of Forbidden Rites",
      "itemId": "4474",
      "armorSet": "Thurgadin",
      "classCode": "CLR"
    },
    {
      "item": "Gauntlets of Forbidden Rites",
      "key": "Gauntlets of Forbidden Rites",
      "itemId": "4475",
      "armorSet": "Thurgadin",
      "classCode": "CLR"
    },
    {
      "item": "Greaves of Forbidden Rites",
      "key": "Greaves of Forbidden Rites",
      "itemId": "4423",
      "armorSet": "Thurgadin",
      "classCode": "CLR"
    },
    {
      "item": "Vambraces of Forbidden Rites",
      "key": "Vambraces of Forbidden Rites",
      "itemId": "4653",
      "armorSet": "Thurgadin",
      "classCode": "CLR"
    },
    {
      "item": "Nature Walker's Boots",
      "key": "Nature Walker's Boots",
      "itemId": "4953",
      "armorSet": "Kael",
      "classCode": "DRU"
    },
    {
      "item": "Nature Walker's Bracer",
      "key": "Nature Walker's Bracer",
      "itemId": "5245",
      "armorSet": "Kael",
      "classCode": "DRU"
    },
    {
      "item": "Nature Walker's Chestguard",
      "key": "Nature Walker's Chestguard",
      "itemId": "4961",
      "armorSet": "Kael",
      "classCode": "DRU"
    },
    {
      "item": "Nature Walker's Circlet",
      "key": "Nature Walker's Circlet",
      "itemId": "5490",
      "armorSet": "Kael",
      "classCode": "DRU"
    },
    {
      "item": "Nature Walker's Gauntlets",
      "key": "Nature Walker's Gauntlets",
      "itemId": "5611",
      "armorSet": "Kael",
      "classCode": "DRU"
    },
    {
      "item": "Nature Walker's Greaves",
      "key": "Nature Walker's Greaves",
      "itemId": "4958",
      "armorSet": "Kael",
      "classCode": "DRU"
    },
    {
      "item": "Nature Walker's Vambraces",
      "key": "Nature Walker's Vambraces",
      "itemId": "5007",
      "armorSet": "Kael",
      "classCode": "DRU"
    },
    {
      "item": "Woven Grass Boots",
      "key": "Woven Grass Boots",
      "itemId": "5153",
      "armorSet": "Skyshrine",
      "classCode": "DRU"
    },
    {
      "item": "Woven Grass Bracelet",
      "key": "Woven Grass Bracelet",
      "itemId": "5246",
      "armorSet": "Skyshrine",
      "classCode": "DRU"
    },
    {
      "item": "Woven Grass Chestguard",
      "key": "Woven Grass Chestguard",
      "itemId": "5180",
      "armorSet": "Skyshrine",
      "classCode": "DRU"
    },
    {
      "item": "Woven Grass Gauntlets",
      "key": "Woven Grass Gauntlets",
      "itemId": "5414",
      "armorSet": "Skyshrine",
      "classCode": "DRU"
    },
    {
      "item": "Woven Grass Greaves",
      "key": "Woven Grass Greaves",
      "itemId": "5526",
      "armorSet": "Skyshrine",
      "classCode": "DRU"
    },
    {
      "item": "Woven Grass Headband",
      "key": "Woven Grass Headband",
      "itemId": "5422",
      "armorSet": "Skyshrine",
      "classCode": "DRU"
    },
    {
      "item": "Woven Grass Vambraces",
      "key": "Woven Grass Vambraces",
      "itemId": "5762",
      "armorSet": "Skyshrine",
      "classCode": "DRU"
    },
    {
      "item": "Rowyl's Boots of Nature",
      "key": "Rowyl's Boots of Nature",
      "itemId": "4345",
      "armorSet": "Thurgadin",
      "classCode": "DRU"
    },
    {
      "item": "Rowyl's Bracer of Nature",
      "key": "Rowyl's Bracer of Nature",
      "itemId": "4126",
      "armorSet": "Thurgadin",
      "classCode": "DRU"
    },
    {
      "item": "Rowyl's Chestguard of Nature",
      "key": "Rowyl's Chestguard of Nature",
      "itemId": "4895",
      "armorSet": "Thurgadin",
      "classCode": "DRU"
    },
    {
      "item": "Rowyl's Circlet of Nature",
      "key": "Rowyl's Circlet of Nature",
      "itemId": "5572",
      "armorSet": "Thurgadin",
      "classCode": "DRU"
    },
    {
      "item": "Rowyl's Gauntlets of Nature",
      "key": "Rowyl's Gauntlets of Nature",
      "itemId": "4520",
      "armorSet": "Thurgadin",
      "classCode": "DRU"
    },
    {
      "item": "Rowyl's Greaves of Nature",
      "key": "Rowyl's Greaves of Nature",
      "itemId": "4127",
      "armorSet": "Thurgadin",
      "classCode": "DRU"
    },
    {
      "item": "Rowyl's Vambraces of Nature",
      "key": "Rowyl's Vambraces of Nature",
      "itemId": "4337",
      "armorSet": "Thurgadin",
      "classCode": "DRU"
    },
    {
      "item": "Dazzling Circlet",
      "key": "Dazzling Circlet",
      "itemId": "5003",
      "armorSet": "Kael",
      "classCode": "ENC"
    },
    {
      "item": "Dazzling Gloves",
      "key": "Dazzling Gloves",
      "itemId": "4668",
      "armorSet": "Kael",
      "classCode": "ENC"
    },
    {
      "item": "Dazzling Robe",
      "key": "Dazzling Robe",
      "itemId": "5078",
      "armorSet": "Kael",
      "classCode": "ENC"
    },
    {
      "item": "Dazzling Sleeves",
      "key": "Dazzling Sleeves",
      "itemId": "5269",
      "armorSet": "Kael",
      "classCode": "ENC"
    },
    {
      "item": "Dazzling Slippers",
      "key": "Dazzling Slippers",
      "itemId": "5004",
      "armorSet": "Kael",
      "classCode": "ENC"
    },
    {
      "item": "Dazzling Trousers",
      "key": "Dazzling Trousers",
      "itemId": "5013",
      "armorSet": "Kael",
      "classCode": "ENC"
    },
    {
      "item": "Dazzling Wristguard",
      "key": "Dazzling Wristguard",
      "itemId": "5131",
      "armorSet": "Kael",
      "classCode": "ENC"
    },
    {
      "item": "Illusionist's Gloves",
      "key": "Illusionist's Gloves",
      "itemId": "5383",
      "armorSet": "Skyshrine",
      "classCode": "ENC"
    },
    {
      "item": "Illusionist's Headband",
      "key": "Illusionist's Headband",
      "itemId": "5736",
      "armorSet": "Skyshrine",
      "classCode": "ENC"
    },
    {
      "item": "Illusionist's Pantaloons",
      "key": "Illusionist's Pantaloons",
      "itemId": "5384",
      "armorSet": "Skyshrine",
      "classCode": "ENC"
    },
    {
      "item": "Illusionist's Robe",
      "key": "Illusionist's Robe",
      "itemId": "5534",
      "armorSet": "Skyshrine",
      "classCode": "ENC"
    },
    {
      "item": "Illusionist's Sleeves",
      "key": "Illusionist's Sleeves",
      "itemId": "5340",
      "armorSet": "Skyshrine",
      "classCode": "ENC"
    },
    {
      "item": "Illusionist's Slippers",
      "key": "Illusionist's Slippers",
      "itemId": "5171",
      "armorSet": "Skyshrine",
      "classCode": "ENC"
    },
    {
      "item": "Illusionist's Wristguard",
      "key": "Illusionist's Wristguard",
      "itemId": "5172",
      "armorSet": "Skyshrine",
      "classCode": "ENC"
    },
    {
      "item": "Beguiler's Crown",
      "key": "Beguiler's Crown",
      "itemId": "4545",
      "armorSet": "Thurgadin",
      "classCode": "ENC"
    },
    {
      "item": "Beguiler's Gloves",
      "key": "Beguiler's Gloves",
      "itemId": "4541",
      "armorSet": "Thurgadin",
      "classCode": "ENC"
    },
    {
      "item": "Beguiler's Robe",
      "key": "Beguiler's Robe",
      "itemId": "4892",
      "armorSet": "Thurgadin",
      "classCode": "ENC"
    },
    {
      "item": "Beguiler's Sleeves",
      "key": "Beguiler's Sleeves",
      "itemId": "4147",
      "armorSet": "Thurgadin",
      "classCode": "ENC"
    },
    {
      "item": "Beguiler's Slippers",
      "key": "Beguiler's Slippers",
      "itemId": "3952",
      "armorSet": "Thurgadin",
      "classCode": "ENC"
    },
    {
      "item": "Beguiler's Trousers",
      "key": "Beguiler's Trousers",
      "itemId": "4872",
      "armorSet": "Thurgadin",
      "classCode": "ENC"
    },
    {
      "item": "Beguiler's Wristguard",
      "key": "Beguiler's Wristguard",
      "itemId": "4771",
      "armorSet": "Thurgadin",
      "classCode": "ENC"
    },
    {
      "item": "Summoner's Boots",
      "key": "Summoner's Boots",
      "itemId": "5720",
      "armorSet": "Kael",
      "classCode": "MAG"
    },
    {
      "item": "Summoner's Circlet",
      "key": "Summoner's Circlet",
      "itemId": "5887",
      "armorSet": "Kael",
      "classCode": "MAG"
    },
    {
      "item": "Summoner's Gloves",
      "key": "Summoner's Gloves",
      "itemId": "6390",
      "armorSet": "Kael",
      "classCode": "MAG"
    },
    {
      "item": "Summoner's Pantaloons",
      "key": "Summoner's Pantaloons",
      "itemId": "5877",
      "armorSet": "Kael",
      "classCode": "MAG"
    },
    {
      "item": "Summoner's Robe",
      "key": "Summoner's Robe",
      "itemId": "5719",
      "armorSet": "Kael",
      "classCode": "MAG"
    },
    {
      "item": "Summoner's Sleeves",
      "key": "Summoner's Sleeves",
      "itemId": "5931",
      "armorSet": "Kael",
      "classCode": "MAG"
    },
    {
      "item": "Summoner's Warband",
      "key": "Summoner's Warband",
      "itemId": "5718",
      "armorSet": "Kael",
      "classCode": "MAG"
    },
    {
      "item": "Prestidigitator's Boots",
      "key": "Prestidigitator's Boots",
      "itemId": "5481",
      "armorSet": "Skyshrine",
      "classCode": "MAG"
    },
    {
      "item": "Prestidigitator's Gloves",
      "key": "Prestidigitator's Gloves",
      "itemId": "5501",
      "armorSet": "Skyshrine",
      "classCode": "MAG"
    },
    {
      "item": "Prestidigitator's Headband",
      "key": "Prestidigitator's Headband",
      "itemId": "5499",
      "armorSet": "Skyshrine",
      "classCode": "MAG"
    },
    {
      "item": "Prestidigitator's Robe",
      "key": "Prestidigitator's Robe",
      "itemId": "5685",
      "armorSet": "Skyshrine",
      "classCode": "MAG"
    },
    {
      "item": "Prestidigitator's Sleeves",
      "key": "Prestidigitator's Sleeves",
      "itemId": "5650",
      "armorSet": "Skyshrine",
      "classCode": "MAG"
    },
    {
      "item": "Prestidigitator's Trousers",
      "key": "Prestidigitator's Trousers",
      "itemId": "5500",
      "armorSet": "Skyshrine",
      "classCode": "MAG"
    },
    {
      "item": "Prestidigitator's Wristband",
      "key": "Prestidigitator's Wristband",
      "itemId": "5651",
      "armorSet": "Skyshrine",
      "classCode": "MAG"
    },
    {
      "item": "Arch Mage's Boots",
      "key": "Arch Mage's Boots",
      "itemId": "4570",
      "armorSet": "Thurgadin",
      "classCode": "MAG"
    },
    {
      "item": "Arch Mage's Crown",
      "key": "Arch Mage's Crown",
      "itemId": "4509",
      "armorSet": "Thurgadin",
      "classCode": "MAG"
    },
    {
      "item": "Arch Mage's Gloves",
      "key": "Arch Mage's Gloves",
      "itemId": "4799",
      "armorSet": "Thurgadin",
      "classCode": "MAG"
    },
    {
      "item": "Arch Mage's Pantaloons",
      "key": "Arch Mage's Pantaloons",
      "itemId": "4701",
      "armorSet": "Thurgadin",
      "classCode": "MAG"
    },
    {
      "item": "Arch Mage's Robe",
      "key": "Arch Mage's Robe",
      "itemId": "5096",
      "armorSet": "Thurgadin",
      "classCode": "MAG"
    },
    {
      "item": "Arch Mage's Sleeves",
      "key": "Arch Mage's Sleeves",
      "itemId": "4843",
      "armorSet": "Thurgadin",
      "classCode": "MAG"
    },
    {
      "item": "Arch Mage's Warband",
      "key": "Arch Mage's Warband",
      "itemId": "4465",
      "armorSet": "Thurgadin",
      "classCode": "MAG"
    },
    {
      "item": "Fist of the Golden Star",
      "key": "Fist of the Golden Star",
      "itemId": "5489",
      "armorSet": "Kael",
      "classCode": "MNK"
    },
    {
      "item": "Golden Star Arm Wraps",
      "key": "Golden Star Arm Wraps",
      "itemId": "4972",
      "armorSet": "Kael",
      "classCode": "MNK"
    },
    {
      "item": "Golden Star Chest Wraps",
      "key": "Golden Star Chest Wraps",
      "itemId": "6224",
      "armorSet": "Kael",
      "classCode": "MNK"
    },
    {
      "item": "Golden Star Headband",
      "key": "Golden Star Headband",
      "itemId": "5448",
      "armorSet": "Kael",
      "classCode": "MNK"
    },
    {
      "item": "Golden Star Pants",
      "key": "Golden Star Pants",
      "itemId": "5174",
      "armorSet": "Kael",
      "classCode": "MNK"
    },
    {
      "item": "Golden Star Slippers",
      "key": "Golden Star Slippers",
      "itemId": "5173",
      "armorSet": "Kael",
      "classCode": "MNK"
    },
    {
      "item": "Golden Star Wrist Wraps",
      "key": "Golden Star Wrist Wraps",
      "itemId": "5447",
      "armorSet": "Kael",
      "classCode": "MNK"
    },
    {
      "item": "Fist of the White Lotus",
      "key": "Fist of the White Lotus",
      "itemId": "6440",
      "armorSet": "Skyshrine",
      "classCode": "MNK"
    },
    {
      "item": "White Lotus Arm Wraps",
      "key": "White Lotus Arm Wraps",
      "itemId": "5482",
      "armorSet": "Skyshrine",
      "classCode": "MNK"
    },
    {
      "item": "White Lotus Chest Wraps",
      "key": "White Lotus Chest Wraps",
      "itemId": "5652",
      "armorSet": "Skyshrine",
      "classCode": "MNK"
    },
    {
      "item": "White Lotus Headband",
      "key": "White Lotus Headband",
      "itemId": "6218",
      "armorSet": "Skyshrine",
      "classCode": "MNK"
    },
    {
      "item": "White Lotus Pants",
      "key": "White Lotus Pants",
      "itemId": "5763",
      "armorSet": "Skyshrine",
      "classCode": "MNK"
    },
    {
      "item": "White Lotus Slippers",
      "key": "White Lotus Slippers",
      "itemId": "5555",
      "armorSet": "Skyshrine",
      "classCode": "MNK"
    },
    {
      "item": "White Lotus Wrist Wraps",
      "key": "White Lotus Wrist Wraps",
      "itemId": "5450",
      "armorSet": "Skyshrine",
      "classCode": "MNK"
    },
    {
      "item": "Fist of the Grand Master",
      "key": "Fist of the Grand Master",
      "itemId": "5331",
      "armorSet": "Thurgadin",
      "classCode": "MNK"
    },
    {
      "item": "Grand Master's Arm Wraps",
      "key": "Grand Master's Arm Wraps",
      "itemId": "4898",
      "armorSet": "Thurgadin",
      "classCode": "MNK"
    },
    {
      "item": "Grand Master's Chest Wraps",
      "key": "Grand Master's Chest Wraps",
      "itemId": "5028",
      "armorSet": "Thurgadin",
      "classCode": "MNK"
    },
    {
      "item": "Grand Master's Headband",
      "key": "Grand Master's Headband",
      "itemId": "4512",
      "armorSet": "Thurgadin",
      "classCode": "MNK"
    },
    {
      "item": "Grand Master's Leg Wraps",
      "key": "Grand Master's Leg Wraps",
      "itemId": "4513",
      "armorSet": "Thurgadin",
      "classCode": "MNK"
    },
    {
      "item": "Grand Master's Slippers",
      "key": "Grand Master's Slippers",
      "itemId": "4698",
      "armorSet": "Thurgadin",
      "classCode": "MNK"
    },
    {
      "item": "Grand Master's Wrist Wraps",
      "key": "Grand Master's Wrist Wraps",
      "itemId": "4514",
      "armorSet": "Thurgadin",
      "classCode": "MNK"
    },
    {
      "item": "Plague Bearer's Boots",
      "key": "Plague Bearer's Boots",
      "itemId": "5122",
      "armorSet": "Kael",
      "classCode": "NEC"
    },
    {
      "item": "Plague Bearer's Circlet",
      "key": "Plague Bearer's Circlet",
      "itemId": "5515",
      "armorSet": "Kael",
      "classCode": "NEC"
    },
    {
      "item": "Plague Bearer's Gloves",
      "key": "Plague Bearer's Gloves",
      "itemId": "4881",
      "armorSet": "Kael",
      "classCode": "NEC"
    },
    {
      "item": "Plague Bearer's Robe",
      "key": "Plague Bearer's Robe",
      "itemId": "5236",
      "armorSet": "Kael",
      "classCode": "NEC"
    },
    {
      "item": "Plague Bearer's Sleeves",
      "key": "Plague Bearer's Sleeves",
      "itemId": "5805",
      "armorSet": "Kael",
      "classCode": "NEC"
    },
    {
      "item": "Plague Bearer's Trousers",
      "key": "Plague Bearer's Trousers",
      "itemId": "6417",
      "armorSet": "Kael",
      "classCode": "NEC"
    },
    {
      "item": "Plague Bearer's Wristguard",
      "key": "Plague Bearer's Wristguard",
      "itemId": "5445",
      "armorSet": "Kael",
      "classCode": "NEC"
    },
    {
      "item": "Rotting Boots",
      "key": "Rotting Boots",
      "itemId": "5423",
      "armorSet": "Skyshrine",
      "classCode": "NEC"
    },
    {
      "item": "Rotting Crown",
      "key": "Rotting Crown",
      "itemId": "5336",
      "armorSet": "Skyshrine",
      "classCode": "NEC"
    },
    {
      "item": "Rotting Gloves",
      "key": "Rotting Gloves",
      "itemId": "5335",
      "armorSet": "Skyshrine",
      "classCode": "NEC"
    },
    {
      "item": "Rotting Robe",
      "key": "Rotting Robe",
      "itemId": "5890",
      "armorSet": "Skyshrine",
      "classCode": "NEC"
    },
    {
      "item": "Rotting Sleeves",
      "key": "Rotting Sleeves",
      "itemId": "5337",
      "armorSet": "Skyshrine",
      "classCode": "NEC"
    },
    {
      "item": "Rotting Trousers",
      "key": "Rotting Trousers",
      "itemId": "5493",
      "armorSet": "Skyshrine",
      "classCode": "NEC"
    },
    {
      "item": "Rotting Wristguard",
      "key": "Rotting Wristguard",
      "itemId": "5764",
      "armorSet": "Skyshrine",
      "classCode": "NEC"
    },
    {
      "item": "Warlock's Boots",
      "key": "Warlock's Boots",
      "itemId": "5005",
      "armorSet": "Thurgadin",
      "classCode": "NEC"
    },
    {
      "item": "Warlock's Crown",
      "key": "Warlock's Crown",
      "itemId": "4584",
      "armorSet": "Thurgadin",
      "classCode": "NEC"
    },
    {
      "item": "Warlock's Gloves",
      "key": "Warlock's Gloves",
      "itemId": "4666",
      "armorSet": "Thurgadin",
      "classCode": "NEC"
    },
    {
      "item": "Warlock's Pantaloons",
      "key": "Warlock's Pantaloons",
      "itemId": "4697",
      "armorSet": "Thurgadin",
      "classCode": "NEC"
    },
    {
      "item": "Warlock's Robe",
      "key": "Warlock's Robe",
      "itemId": "4968",
      "armorSet": "Thurgadin",
      "classCode": "NEC"
    },
    {
      "item": "Warlock's Sleeves",
      "key": "Warlock's Sleeves",
      "itemId": "4601",
      "armorSet": "Thurgadin",
      "classCode": "NEC"
    },
    {
      "item": "Warlock's Wristguard",
      "key": "Warlock's Wristguard",
      "itemId": "4891",
      "armorSet": "Thurgadin",
      "classCode": "NEC"
    },
    {
      "item": "Shining Boots",
      "key": "Shining Boots",
      "itemId": "5121",
      "armorSet": "Kael",
      "classCode": "PAL"
    },
    {
      "item": "Shining Bracer",
      "key": "Shining Bracer",
      "itemId": "5097",
      "armorSet": "Kael",
      "classCode": "PAL"
    },
    {
      "item": "Shining Breastplate",
      "key": "Shining Breastplate",
      "itemId": "5226",
      "armorSet": "Kael",
      "classCode": "PAL"
    },
    {
      "item": "Shining Gauntlets",
      "key": "Shining Gauntlets",
      "itemId": "4790",
      "armorSet": "Kael",
      "classCode": "PAL"
    },
    {
      "item": "Shining Greaves",
      "key": "Shining Greaves",
      "itemId": "5248",
      "armorSet": "Kael",
      "classCode": "PAL"
    },
    {
      "item": "Shining Helm",
      "key": "Shining Helm",
      "itemId": "5148",
      "armorSet": "Kael",
      "classCode": "PAL"
    },
    {
      "item": "Shining Vambraces",
      "key": "Shining Vambraces",
      "itemId": "5325",
      "armorSet": "Kael",
      "classCode": "PAL"
    },
    {
      "item": "Scaled Knight's Boots",
      "key": "Scaled Knight's Boots",
      "itemId": "5728",
      "armorSet": "Skyshrine",
      "classCode": "PAL"
    },
    {
      "item": "Scaled Knight's Bracer",
      "key": "Scaled Knight's Bracer",
      "itemId": "5451",
      "armorSet": "Skyshrine",
      "classCode": "PAL"
    },
    {
      "item": "Scaled Knight's Breastplate",
      "key": "Scaled Knight's Breastplate",
      "itemId": "5735",
      "armorSet": "Skyshrine",
      "classCode": "PAL"
    },
    {
      "item": "Scaled Knight's Gauntlets",
      "key": "Scaled Knight's Gauntlets",
      "itemId": "5993",
      "armorSet": "Skyshrine",
      "classCode": "PAL"
    },
    {
      "item": "Scaled Knight's Greaves",
      "key": "Scaled Knight's Greaves",
      "itemId": "5452",
      "armorSet": "Skyshrine",
      "classCode": "PAL"
    },
    {
      "item": "Scaled Knight's Helm",
      "key": "Scaled Knight's Helm",
      "itemId": "5791",
      "armorSet": "Skyshrine",
      "classCode": "PAL"
    },
    {
      "item": "Scaled Knight's Vambraces",
      "key": "Scaled Knight's Vambraces",
      "itemId": "5232",
      "armorSet": "Skyshrine",
      "classCode": "PAL"
    },
    {
      "item": "Runed Protector's Boots",
      "key": "Runed Protector's Boots",
      "itemId": "4343",
      "armorSet": "Thurgadin",
      "classCode": "PAL"
    },
    {
      "item": "Runed Protector's Bracer",
      "key": "Runed Protector's Bracer",
      "itemId": "4533",
      "armorSet": "Thurgadin",
      "classCode": "PAL"
    },
    {
      "item": "Runed Protector's Breastplate",
      "key": "Runed Protector's Breastplate",
      "itemId": "4562",
      "armorSet": "Thurgadin",
      "classCode": "PAL"
    },
    {
      "item": "Runed Protector's Gauntlets",
      "key": "Runed Protector's Gauntlets",
      "itemId": "4327",
      "armorSet": "Thurgadin",
      "classCode": "PAL"
    },
    {
      "item": "Runed Protector's Greaves",
      "key": "Runed Protector's Greaves",
      "itemId": "4370",
      "armorSet": "Thurgadin",
      "classCode": "PAL"
    },
    {
      "item": "Runed Protector's Helm",
      "key": "Runed Protector's Helm",
      "itemId": "5346",
      "armorSet": "Thurgadin",
      "classCode": "PAL"
    },
    {
      "item": "Runed Protector's Vambraces",
      "key": "Runed Protector's Vambraces",
      "itemId": "4221",
      "armorSet": "Thurgadin",
      "classCode": "PAL"
    },
    {
      "item": "Forest Stalker's Boots",
      "key": "Forest Stalker's Boots",
      "itemId": "5261",
      "armorSet": "Kael",
      "classCode": "RNG"
    },
    {
      "item": "Forest Stalker's Bracer",
      "key": "Forest Stalker's Bracer",
      "itemId": "5147",
      "armorSet": "Kael",
      "classCode": "RNG"
    },
    {
      "item": "Forest Stalker's Breastplate",
      "key": "Forest Stalker's Breastplate",
      "itemId": "5300",
      "armorSet": "Kael",
      "classCode": "RNG"
    },
    {
      "item": "Forest Stalker's Coif",
      "key": "Forest Stalker's Coif",
      "itemId": "4880",
      "armorSet": "Kael",
      "classCode": "RNG"
    },
    {
      "item": "Forest Stalker's Gauntlets",
      "key": "Forest Stalker's Gauntlets",
      "itemId": "5146",
      "armorSet": "Kael",
      "classCode": "RNG"
    },
    {
      "item": "Forest Stalker's Greaves",
      "key": "Forest Stalker's Greaves",
      "itemId": "5098",
      "armorSet": "Kael",
      "classCode": "RNG"
    },
    {
      "item": "Forest Stalker's Vambraces",
      "key": "Forest Stalker's Vambraces",
      "itemId": "5144",
      "armorSet": "Kael",
      "classCode": "RNG"
    },
    {
      "item": "Golden Leaf Boots",
      "key": "Golden Leaf Boots",
      "itemId": "5313",
      "armorSet": "Skyshrine",
      "classCode": "RNG"
    },
    {
      "item": "Golden Leaf Bracer",
      "key": "Golden Leaf Bracer",
      "itemId": "5312",
      "armorSet": "Skyshrine",
      "classCode": "RNG"
    },
    {
      "item": "Golden Leaf Breastplate",
      "key": "Golden Leaf Breastplate",
      "itemId": "5354",
      "armorSet": "Skyshrine",
      "classCode": "RNG"
    },
    {
      "item": "Golden Leaf Gauntlets",
      "key": "Golden Leaf Gauntlets",
      "itemId": "5152",
      "armorSet": "Skyshrine",
      "classCode": "RNG"
    },
    {
      "item": "Golden Leaf Greaves",
      "key": "Golden Leaf Greaves",
      "itemId": "6095",
      "armorSet": "Skyshrine",
      "classCode": "RNG"
    },
    {
      "item": "Golden Leaf Helm",
      "key": "Golden Leaf Helm",
      "itemId": "5483",
      "armorSet": "Skyshrine",
      "classCode": "RNG"
    },
    {
      "item": "Golden Leaf Vambraces",
      "key": "Golden Leaf Vambraces",
      "itemId": "5151",
      "armorSet": "Skyshrine",
      "classCode": "RNG"
    },
    {
      "item": "Runed Scout's Boots",
      "key": "Runed Scout's Boots",
      "itemId": "4283",
      "armorSet": "Thurgadin",
      "classCode": "RNG"
    },
    {
      "item": "Runed Scout's Bracer",
      "key": "Runed Scout's Bracer",
      "itemId": "4476",
      "armorSet": "Thurgadin",
      "classCode": "RNG"
    },
    {
      "item": "Runed Scout's Breastplate",
      "key": "Runed Scout's Breastplate",
      "itemId": "4928",
      "armorSet": "Thurgadin",
      "classCode": "RNG"
    },
    {
      "item": "Runed Scout's Gauntlets",
      "key": "Runed Scout's Gauntlets",
      "itemId": "4699",
      "armorSet": "Thurgadin",
      "classCode": "RNG"
    },
    {
      "item": "Runed Scout's Greaves",
      "key": "Runed Scout's Greaves",
      "itemId": "5063",
      "armorSet": "Thurgadin",
      "classCode": "RNG"
    },
    {
      "item": "Runed Scout's Helm",
      "key": "Runed Scout's Helm",
      "itemId": "4713",
      "armorSet": "Thurgadin",
      "classCode": "RNG"
    },
    {
      "item": "Runed Scout's Vambraces",
      "key": "Runed Scout's Vambraces",
      "itemId": "4371",
      "armorSet": "Thurgadin",
      "classCode": "RNG"
    },
    {
      "item": "Deceiver's Boots",
      "key": "Deceiver's Boots",
      "itemId": "5730",
      "armorSet": "Kael",
      "classCode": "ROG"
    },
    {
      "item": "Deceiver's Bracer",
      "key": "Deceiver's Bracer",
      "itemId": "5233",
      "armorSet": "Kael",
      "classCode": "ROG"
    },
    {
      "item": "Deceiver's Chestguard",
      "key": "Deceiver's Chestguard",
      "itemId": "5167",
      "armorSet": "Kael",
      "classCode": "ROG"
    },
    {
      "item": "Deceiver's Crown",
      "key": "Deceiver's Crown",
      "itemId": "5011",
      "armorSet": "Kael",
      "classCode": "ROG"
    },
    {
      "item": "Deceiver's Gauntlets",
      "key": "Deceiver's Gauntlets",
      "itemId": "5141",
      "armorSet": "Kael",
      "classCode": "ROG"
    },
    {
      "item": "Deceiver's Greaves",
      "key": "Deceiver's Greaves",
      "itemId": "6012",
      "armorSet": "Kael",
      "classCode": "ROG"
    },
    {
      "item": "Deceiver's Vambraces",
      "key": "Deceiver's Vambraces",
      "itemId": "5010",
      "armorSet": "Kael",
      "classCode": "ROG"
    },
    {
      "item": "Shadow Boots",
      "key": "Shadow Boots",
      "itemId": "5528",
      "armorSet": "Skyshrine",
      "classCode": "ROG"
    },
    {
      "item": "Shadow Bracer",
      "key": "Shadow Bracer",
      "itemId": "5503",
      "armorSet": "Skyshrine",
      "classCode": "ROG"
    },
    {
      "item": "Shadow Chestguard",
      "key": "Shadow Chestguard",
      "itemId": "5260",
      "armorSet": "Skyshrine",
      "classCode": "ROG"
    },
    {
      "item": "Shadow Crown",
      "key": "Shadow Crown",
      "itemId": "5485",
      "armorSet": "Skyshrine",
      "classCode": "ROG"
    },
    {
      "item": "Shadow Gauntlets",
      "key": "Shadow Gauntlets",
      "itemId": "6416",
      "armorSet": "Skyshrine",
      "classCode": "ROG"
    },
    {
      "item": "Shadow Greaves",
      "key": "Shadow Greaves",
      "itemId": "5139",
      "armorSet": "Skyshrine",
      "classCode": "ROG"
    },
    {
      "item": "Shadow Vambraces",
      "key": "Shadow Vambraces",
      "itemId": "5484",
      "armorSet": "Skyshrine",
      "classCode": "ROG"
    },
    {
      "item": "Brigand's Boots",
      "key": "Brigand's Boots",
      "itemId": "4561",
      "armorSet": "Thurgadin",
      "classCode": "ROG"
    },
    {
      "item": "Brigand's Bracer",
      "key": "Brigand's Bracer",
      "itemId": "5479",
      "armorSet": "Thurgadin",
      "classCode": "ROG"
    },
    {
      "item": "Brigand's Chestguard",
      "key": "Brigand's Chestguard",
      "itemId": "4981",
      "armorSet": "Thurgadin",
      "classCode": "ROG"
    },
    {
      "item": "Brigand's Circlet",
      "key": "Brigand's Circlet",
      "itemId": "4980",
      "armorSet": "Thurgadin",
      "classCode": "ROG"
    },
    {
      "item": "Brigand's Gauntlets",
      "key": "Brigand's Gauntlets",
      "itemId": "4979",
      "armorSet": "Thurgadin",
      "classCode": "ROG"
    },
    {
      "item": "Brigand's Greaves",
      "key": "Brigand's Greaves",
      "itemId": "5637",
      "armorSet": "Thurgadin",
      "classCode": "ROG"
    },
    {
      "item": "Brigand's Vambraces",
      "key": "Brigand's Vambraces",
      "itemId": "4996",
      "armorSet": "Thurgadin",
      "classCode": "ROG"
    },
    {
      "item": "Malevolent Boots",
      "key": "Malevolent Boots",
      "itemId": "5012",
      "armorSet": "Kael",
      "classCode": "SHD"
    },
    {
      "item": "Malevolent Bracer",
      "key": "Malevolent Bracer",
      "itemId": "5023",
      "armorSet": "Kael",
      "classCode": "SHD"
    },
    {
      "item": "Malevolent Breastplate",
      "key": "Malevolent Breastplate",
      "itemId": "6225",
      "armorSet": "Kael",
      "classCode": "SHD"
    },
    {
      "item": "Malevolent Crown",
      "key": "Malevolent Crown",
      "itemId": "5006",
      "armorSet": "Kael",
      "classCode": "SHD"
    },
    {
      "item": "Malevolent Gauntlets",
      "key": "Malevolent Gauntlets",
      "itemId": "5024",
      "armorSet": "Kael",
      "classCode": "SHD"
    },
    {
      "item": "Malevolent Greaves",
      "key": "Malevolent Greaves",
      "itemId": "5866",
      "armorSet": "Kael",
      "classCode": "SHD"
    },
    {
      "item": "Malevolent Vambraces",
      "key": "Malevolent Vambraces",
      "itemId": "6299",
      "armorSet": "Kael",
      "classCode": "SHD"
    },
    {
      "item": "Blood Lord's Boots",
      "key": "Blood Lord's Boots",
      "itemId": "5647",
      "armorSet": "Skyshrine",
      "classCode": "SHD"
    },
    {
      "item": "Blood Lord's Bracer",
      "key": "Blood Lord's Bracer",
      "itemId": "5644",
      "armorSet": "Skyshrine",
      "classCode": "SHD"
    },
    {
      "item": "Blood Lord's Breastplate",
      "key": "Blood Lord's Breastplate",
      "itemId": "5737",
      "armorSet": "Skyshrine",
      "classCode": "SHD"
    },
    {
      "item": "Blood Lord's Crown",
      "key": "Blood Lord's Crown",
      "itemId": "5646",
      "armorSet": "Skyshrine",
      "classCode": "SHD"
    },
    {
      "item": "Blood Lord's Gauntlets",
      "key": "Blood Lord's Gauntlets",
      "itemId": "5645",
      "armorSet": "Skyshrine",
      "classCode": "SHD"
    },
    {
      "item": "Blood Lord's Greaves",
      "key": "Blood Lord's Greaves",
      "itemId": "5803",
      "armorSet": "Skyshrine",
      "classCode": "SHD"
    },
    {
      "item": "Blood Lord's Vambraces",
      "key": "Blood Lord's Vambraces",
      "itemId": "6219",
      "armorSet": "Skyshrine",
      "classCode": "SHD"
    },
    {
      "item": "Dark Runed Boots",
      "key": "Dark Runed Boots",
      "itemId": "4603",
      "armorSet": "Thurgadin",
      "classCode": "SHD"
    },
    {
      "item": "Dark Runed Bracer",
      "key": "Dark Runed Bracer",
      "itemId": "4602",
      "armorSet": "Thurgadin",
      "classCode": "SHD"
    },
    {
      "item": "Dark Runed Breastplate",
      "key": "Dark Runed Breastplate",
      "itemId": "5889",
      "armorSet": "Thurgadin",
      "classCode": "SHD"
    },
    {
      "item": "Dark Runed Crown",
      "key": "Dark Runed Crown",
      "itemId": "5598",
      "armorSet": "Thurgadin",
      "classCode": "SHD"
    },
    {
      "item": "Dark Runed Gauntlets",
      "key": "Dark Runed Gauntlets",
      "itemId": "4547",
      "armorSet": "Thurgadin",
      "classCode": "SHD"
    },
    {
      "item": "Dark Runed Greaves",
      "key": "Dark Runed Greaves",
      "itemId": "4627",
      "armorSet": "Thurgadin",
      "classCode": "SHD"
    },
    {
      "item": "Dark Runed Vambraces",
      "key": "Dark Runed Vambraces",
      "itemId": "5027",
      "armorSet": "Thurgadin",
      "classCode": "SHD"
    },
    {
      "item": "Spirit Caller's Boots",
      "key": "Spirit Caller's Boots",
      "itemId": "5142",
      "armorSet": "Kael",
      "classCode": "SHM"
    },
    {
      "item": "Spirit Caller's Bracer",
      "key": "Spirit Caller's Bracer",
      "itemId": "4986",
      "armorSet": "Kael",
      "classCode": "SHM"
    },
    {
      "item": "Spirit Caller's Breastplate",
      "key": "Spirit Caller's Breastplate",
      "itemId": "5124",
      "armorSet": "Kael",
      "classCode": "SHM"
    },
    {
      "item": "Spirit Caller's Gauntlets",
      "key": "Spirit Caller's Gauntlets",
      "itemId": "5025",
      "armorSet": "Kael",
      "classCode": "SHM"
    },
    {
      "item": "Spirit Caller's Greaves",
      "key": "Spirit Caller's Greaves",
      "itemId": "5130",
      "armorSet": "Kael",
      "classCode": "SHM"
    },
    {
      "item": "Spirit Caller's Helm",
      "key": "Spirit Caller's Helm",
      "itemId": "5302",
      "armorSet": "Kael",
      "classCode": "SHM"
    },
    {
      "item": "Spirit Caller's Vambraces",
      "key": "Spirit Caller's Vambraces",
      "itemId": "4997",
      "armorSet": "Kael",
      "classCode": "SHM"
    },
    {
      "item": "Wolf Caller's Boots",
      "key": "Wolf Caller's Boots",
      "itemId": "5782",
      "armorSet": "Skyshrine",
      "classCode": "SHM"
    },
    {
      "item": "Wolf Caller's Bracer",
      "key": "Wolf Caller's Bracer",
      "itemId": "5786",
      "armorSet": "Skyshrine",
      "classCode": "SHM"
    },
    {
      "item": "Wolf Caller's Breastplate",
      "key": "Wolf Caller's Breastplate",
      "itemId": "5781",
      "armorSet": "Skyshrine",
      "classCode": "SHM"
    },
    {
      "item": "Wolf Caller's Gauntlets",
      "key": "Wolf Caller's Gauntlets",
      "itemId": "5785",
      "armorSet": "Skyshrine",
      "classCode": "SHM"
    },
    {
      "item": "Wolf Caller's Greaves",
      "key": "Wolf Caller's Greaves",
      "itemId": "5425",
      "armorSet": "Skyshrine",
      "classCode": "SHM"
    },
    {
      "item": "Wolf Caller's Helm",
      "key": "Wolf Caller's Helm",
      "itemId": "5784",
      "armorSet": "Skyshrine",
      "classCode": "SHM"
    },
    {
      "item": "Wolf Caller's Vambraces",
      "key": "Wolf Caller's Vambraces",
      "itemId": "5783",
      "armorSet": "Skyshrine",
      "classCode": "SHM"
    },
    {
      "item": "Rune Crafter's Boots",
      "key": "Rune Crafter's Boots",
      "itemId": "4438",
      "armorSet": "Thurgadin",
      "classCode": "SHM"
    },
    {
      "item": "Rune Crafter's Bracer",
      "key": "Rune Crafter's Bracer",
      "itemId": "4300",
      "armorSet": "Thurgadin",
      "classCode": "SHM"
    },
    {
      "item": "Rune Crafter's Breastplate",
      "key": "Rune Crafter's Breastplate",
      "itemId": "4995",
      "armorSet": "Thurgadin",
      "classCode": "SHM"
    },
    {
      "item": "Rune Crafter's Gauntlets",
      "key": "Rune Crafter's Gauntlets",
      "itemId": "4422",
      "armorSet": "Thurgadin",
      "classCode": "SHM"
    },
    {
      "item": "Rune Crafter's Greaves",
      "key": "Rune Crafter's Greaves",
      "itemId": "4866",
      "armorSet": "Thurgadin",
      "classCode": "SHM"
    },
    {
      "item": "Rune Crafter's Helm",
      "key": "Rune Crafter's Helm",
      "itemId": "4994",
      "armorSet": "Thurgadin",
      "classCode": "SHM"
    },
    {
      "item": "Rune Crafter's Vambraces",
      "key": "Rune Crafter's Vambraces",
      "itemId": "4583",
      "armorSet": "Thurgadin",
      "classCode": "SHM"
    },
    {
      "item": "Warlord's Boots",
      "key": "Warlord's Boots",
      "itemId": "4857",
      "armorSet": "Kael",
      "classCode": "WAR"
    },
    {
      "item": "Warlord's Bracer",
      "key": "Warlord's Bracer",
      "itemId": "4856",
      "armorSet": "Kael",
      "classCode": "WAR"
    },
    {
      "item": "Warlord's Breastplate",
      "key": "Warlord's Breastplate",
      "itemId": "4984",
      "armorSet": "Kael",
      "classCode": "WAR"
    },
    {
      "item": "Warlord's Crown",
      "key": "Warlord's Crown",
      "itemId": "5178",
      "armorSet": "Kael",
      "classCode": "WAR"
    },
    {
      "item": "Warlord's Gauntlets",
      "key": "Warlord's Gauntlets",
      "itemId": "5128",
      "armorSet": "Kael",
      "classCode": "WAR"
    },
    {
      "item": "Warlord's Greaves",
      "key": "Warlord's Greaves",
      "itemId": "4858",
      "armorSet": "Kael",
      "classCode": "WAR"
    },
    {
      "item": "Warlord's Vambraces",
      "key": "Warlord's Vambraces",
      "itemId": "5149",
      "armorSet": "Kael",
      "classCode": "WAR"
    },
    {
      "item": "Boots of the Myrmidon",
      "key": "Boots of the Myrmidon",
      "itemId": "5326",
      "armorSet": "Skyshrine",
      "classCode": "WAR"
    },
    {
      "item": "Bracer of the Myrmidon",
      "key": "Bracer of the Myrmidon",
      "itemId": "5556",
      "armorSet": "Skyshrine",
      "classCode": "WAR"
    },
    {
      "item": "Breastplate of the Myrmidon",
      "key": "Breastplate of the Myrmidon",
      "itemId": "5505",
      "armorSet": "Skyshrine",
      "classCode": "WAR"
    },
    {
      "item": "Crown of the Myrmidon",
      "key": "Crown of the Myrmidon",
      "itemId": "5358",
      "armorSet": "Skyshrine",
      "classCode": "WAR"
    },
    {
      "item": "Gauntlets of the Myrmidon",
      "key": "Gauntlets of the Myrmidon",
      "itemId": "5550",
      "armorSet": "Skyshrine",
      "classCode": "WAR"
    },
    {
      "item": "Greaves of the Myrmidon",
      "key": "Greaves of the Myrmidon",
      "itemId": "5420",
      "armorSet": "Skyshrine",
      "classCode": "WAR"
    },
    {
      "item": "Vambraces of the Myrmidon",
      "key": "Vambraces of the Myrmidon",
      "itemId": "5421",
      "armorSet": "Skyshrine",
      "classCode": "WAR"
    },
    {
      "item": "Champion's Boots",
      "key": "Champion's Boots",
      "itemId": "5064",
      "armorSet": "Thurgadin",
      "classCode": "WAR"
    },
    {
      "item": "Champion's Bracer",
      "key": "Champion's Bracer",
      "itemId": "4288",
      "armorSet": "Thurgadin",
      "classCode": "WAR"
    },
    {
      "item": "Champion's Breastplate",
      "key": "Champion's Breastplate",
      "itemId": "4969",
      "armorSet": "Thurgadin",
      "classCode": "WAR"
    },
    {
      "item": "Champion's Crown",
      "key": "Champion's Crown",
      "itemId": "4516",
      "armorSet": "Thurgadin",
      "classCode": "WAR"
    },
    {
      "item": "Champion's Gauntlets",
      "key": "Champion's Gauntlets",
      "itemId": "4521",
      "armorSet": "Thurgadin",
      "classCode": "WAR"
    },
    {
      "item": "Champion's Greaves",
      "key": "Champion's Greaves",
      "itemId": "5099",
      "armorSet": "Thurgadin",
      "classCode": "WAR"
    },
    {
      "item": "Champion's Vambraces",
      "key": "Champion's Vambraces",
      "itemId": "4515",
      "armorSet": "Thurgadin",
      "classCode": "WAR"
    },
    {
      "item": "Bangle of the Invoker",
      "key": "Bangle of the Invoker",
      "itemId": "5412",
      "armorSet": "Kael",
      "classCode": "WIZ"
    },
    {
      "item": "Boots of the Invoker",
      "key": "Boots of the Invoker",
      "itemId": "5255",
      "armorSet": "Kael",
      "classCode": "WIZ"
    },
    {
      "item": "Circlet of the Invoker",
      "key": "Circlet of the Invoker",
      "itemId": "5123",
      "armorSet": "Kael",
      "classCode": "WIZ"
    },
    {
      "item": "Gloves of the Invoker",
      "key": "Gloves of the Invoker",
      "itemId": "5065",
      "armorSet": "Kael",
      "classCode": "WIZ"
    },
    {
      "item": "Pants of the Invoker",
      "key": "Pants of the Invoker",
      "itemId": "5231",
      "armorSet": "Kael",
      "classCode": "WIZ"
    },
    {
      "item": "Robe of the Invoker",
      "key": "Robe of the Invoker",
      "itemId": "5234",
      "armorSet": "Kael",
      "classCode": "WIZ"
    },
    {
      "item": "Sleeves of the Invoker",
      "key": "Sleeves of the Invoker",
      "itemId": "5393",
      "armorSet": "Kael",
      "classCode": "WIZ"
    },
    {
      "item": "Icicle Boots",
      "key": "Icicle Boots",
      "itemId": "5601",
      "armorSet": "Skyshrine",
      "classCode": "WIZ"
    },
    {
      "item": "Icicle Bracelet",
      "key": "Icicle Bracelet",
      "itemId": "4962",
      "armorSet": "Skyshrine",
      "classCode": "WIZ"
    },
    {
      "item": "Icicle Circlet",
      "key": "Icicle Circlet",
      "itemId": "6319",
      "armorSet": "Skyshrine",
      "classCode": "WIZ"
    },
    {
      "item": "Icicle Gloves",
      "key": "Icicle Gloves",
      "itemId": "5311",
      "armorSet": "Skyshrine",
      "classCode": "WIZ"
    },
    {
      "item": "Icicle Pantaloons",
      "key": "Icicle Pantaloons",
      "itemId": "5486",
      "armorSet": "Skyshrine",
      "classCode": "WIZ"
    },
    {
      "item": "Icicle Sleeves",
      "key": "Icicle Sleeves",
      "itemId": "5181",
      "armorSet": "Skyshrine",
      "classCode": "WIZ"
    },
    {
      "item": "Robe of Icicles",
      "key": "Robe of Icicles",
      "itemId": "5770",
      "armorSet": "Skyshrine",
      "classCode": "WIZ"
    },
    {
      "item": "Sage's Boots",
      "key": "Sage's Boots",
      "itemId": "6111",
      "armorSet": "Thurgadin",
      "classCode": "WIZ"
    },
    {
      "item": "Sage's Bracelet",
      "key": "Sage's Bracelet",
      "itemId": "4517",
      "armorSet": "Thurgadin",
      "classCode": "WIZ"
    },
    {
      "item": "Sage's Crown",
      "key": "Sage's Crown",
      "itemId": "5769",
      "armorSet": "Thurgadin",
      "classCode": "WIZ"
    },
    {
      "item": "Sage's Gloves",
      "key": "Sage's Gloves",
      "itemId": "4660",
      "armorSet": "Thurgadin",
      "classCode": "WIZ"
    },
    {
      "item": "Sage's Pantaloons",
      "key": "Sage's Pantaloons",
      "itemId": "6110",
      "armorSet": "Thurgadin",
      "classCode": "WIZ"
    },
    {
      "item": "Sage's Robe",
      "key": "Sage's Robe",
      "itemId": "4786",
      "armorSet": "Thurgadin",
      "classCode": "WIZ"
    },
    {
      "item": "Sage's Sleeves",
      "key": "Sage's Sleeves",
      "itemId": "5495",
      "armorSet": "Thurgadin",
      "classCode": "WIZ"
    }
  ],
  "failed": [],
  "skippedClasses": [],
  "staleImportedRecordsRemoved": []
}
